Workbook

Sheet README
A1: Workbook guide
A3: How to use
A4: • Start on the Dashboard tab for high-level KPIs and charts.
A5: • Use the navigation links on the Dashboard (and the 'Home' link on each sheet) to jump around.
A6: • The Detail tab contains all 867 line items from Project_Detail.csv (filterable).
A7: • Summary tabs (Packages/CBS/Methods) roll up Detail using Excel formulas (SUMIFS/COUNTIFS).
A8: • Assumptions and Risks tabs contain the consolidated registers from the markdown files.
A9: • Inputs tab contains mappings (Package → Category) and contingency rates by CBS bucket.
A12: Notes
A13: Contingency in BOE has minor internal inconsistencies (Executive Summary vs bucket table). This workbook uses the BOE §7.2 bucket rates for calculations and shows the delta vs the BOE stated total.
A15: Data sources (local files)
A16: • Project_Detail.csv
... A21: Go to Dashboard

Sheet Dashboard
A1: Canola Oil Transload Facility — Estimate Dashboard
A2: Data snapshot: 2026-01-29 (from source files)
A4: Navigate: | C4: Base estimate (calc.) | F4: Contingency (calc.) | I4: Total estimate (calc.)
A5: Package roll-up | C5: =Summary_CBS!B12 | F5: =Summary_CBS!D12 | I5: =Summary_CBS!E12
A6: CBS roll-up
A7: Pricing methods
A8: All line items (867)
A9: Assumptions (groups) | C9: BOE stated total | F9: BOE stated contingency | I9: Delta (calc - BOE)
A10: Assumptions (items) | C10: 117100000 | F10: 24700000 | I10: =I5-C10
A11: Risks (groups)
A12: Risks (items)
A13: BOE reference
A14: Inputs / lookups | C14: # Packages | F14: # Deliverables | I14: # Line items
A15: Read me | C15: 36 | F15: 202 | I15: 867
C19: Assumptions (groups) | F19: Assumptions (raw) | I19: Risks (groups)
C20: 311 | F20: 588 | I20: 120
C24: Risks (raw) | F24: Pricing date | I24: Estimate class
C25: 297 | F25: January 2026 | I25: Class 5 (Order of Magnitude)
A30: Charts
A32: Package | B32: Total | C32: Category
A33: PKG-13 | B33: =SUMIFS(Detail!$U$2:$U$868,Detail!$F$2:$F$868,$A33) | C33: =VLOOKUP($A33,Inputs!$D$6:$E$41,2,FALSE)
A34: PKG-08 | B34: =SUMIFS(Detail!$U$2:$U$868,Detail!$F$2:$F$868,$A34) | C34: =VLOOKUP($A34,Inputs!$D$6:$E$41,2,FALSE)
A35: PKG-14 | B35: =SUMIFS(Detail!$U$2:$U$868,Detail!$F$2:$F$868,$A35) | C35: =VLOOKUP($A35,Inputs!$D$6:$E$41,2,FALSE)
A36: PKG-30 | B36: =SUMIFS(Detail!$U$2:$U$868,Detail!$F$2:$F$868,$A36) | C36: =VLOOKUP($A36,Inputs!$D$6:$E$41,2,FALSE)
A37: PKG-04 | B37: =SUMIFS(Detail!$U$2:$U$868,Detail!$F$2:$F$868,$A37) | C37: =VLOOKUP($A37,Inputs!$D$6:$E$41,2,FALSE)
A38: PKG-10 | B38: =SUMIFS(Detail!$U$2:$U$868,Detail!$F$2:$F$868,$A38) | C38: =VLOOKUP($A38,Inputs!$D$6:$E$41,2,FALSE)
A39: PKG-17 | B39: =SUMIFS(Detail!$U$2:$U$868,Detail!$F$2:$F$868,$A39) | C39: =VLOOKUP($A39,Inputs!$D$6:$E$41,2,FALSE)
A40: PKG-02 | B40: =SUMIFS(Detail!$U$2:$U$868,Detail!$F$2:$F$868,$A40) | C40: =VLOOKUP($A40,Inputs!$D$6:$E$41,2,FALSE)
A41: PKG-16 | B41: =SUMIFS(Detail!$U$2:$U$868,Detail!$F$2:$F$868,$A41) | C41: =VLOOKUP($A41,Inputs!$D$6:$E$41,2,FALSE)
A42: PKG-26 | B42: =SUMIFS(Detail!$U$2:$U$868,Detail!$F$2:$F$868,$A42) | C42: =VLOOKUP($A42,Inputs!$D$6:$E$41,2,FALSE)
A45: Category | B45: Base
A46: Site & Civil | B46: =SUMIFS(Detail!$L$2:$L$868,Detail!$R$2:$R$868,$A46)
A47: Structural | B47: =SUMIFS(Detail!$L$2:$L$868,Detail!$R$2:$R$868,$A47)
A48: Mechanical | B48: =SUMIFS(Detail!$L$2:$L$868,Detail!$R$2:$R$868,$A48)
A49: Electrical & I&C | B49: =SUMIFS(Detail!$L$2:$L$868,Detail!$R$2:$R$868,$A49)
A50: Buildings & Protection | B50: =SUMIFS(Detail!$L$2:$L$868,Detail!$R$2:$R$868,$A50)
A51: Project Execution | B51: =SUMIFS(Detail!$L$2:$L$868,Detail!$R$2:$R$868,$A51)
A56: Risk category | B56: Groups
A57: UNCATEGORIZED | B57: 46
A58: RSK-SCOPE | B58: 27
A59: RSK-INTF | B59: 15
A60: RSK-TECH | B60: 8
A61: RSK-PRICE | B61: 7
A62: RSK-QUAL | B62: 4
A63: RSK-SCHED | B63: 4
A64: RSK-QTY | B64: 3
A65: RSK-ENV | B65: 2
A66: RSK-PROD | B66: 2
A67: RSK-ESC | B67: 1
A68: Assumption category | B68: Groups
A69: ASM-PRICE | B69: 123
A70: UNCATEGORIZED | B70: 96
A71: ASM-LABOR | B71: 28
A72: ASM-QTY | B72: 17
A73: ASM-INTF | B73: 13
A74: ASM-ENG | B74: 12
A75: ASM-TECH | B75: 12
A76: ASM-SCOPE | B76: 10

Sheet Summary_Packages
A1: Package summary (computed from Detail) | J1: Home
A3: Package | B3: Description | C3: PackageCategory | D3: Confidence | E3: Base | F3: Contingency | G3: Total | H3: LineItems
A4: PKG-00 | B4: Site Establishment | C4: Site & Civil | D4: LOW | E4: =SUMIFS(Detail!$L$2:$L$868,Detail!$F$2:$F$868,$A4) | F4: =SUMIFS(Detail!$T$2:$T$868,Detail!$F$2:$F$868,$A4) | G4: =$E4+$F4 | H4: =COUNTIF(Detail!$F$2:$F$868,$A4)
A5: PKG-01 | B5: Demolition & Removals | C5: Site & Civil | D5: LOW | E5: =SUMIFS(Detail!$L$2:$L$868,Detail!$F$2:$F$868,$A5) | F5: =SUMIFS(Detail!$T$2:$T$868,Detail!$F$2:$F$868,$A5) | G5: =$E5+$F5 | H5: =COUNTIF(Detail!$F$2:$F$868,$A5)
A6: PKG-02 | B6: Earthworks & Ground Improvement | C6: Site & Civil | D6: LOW | E6: =SUMIFS(Detail!$L$2:$L$868,Detail!$F$2:$F$868,$A6) | F6: =SUMIFS(Detail!$T$2:$T$868,Detail!$F$2:$F$868,$A6) | G6: =$E6+$F6 | H6: =COUNTIF(Detail!$F$2:$F$868,$A6)
A7: PKG-03 | B7: Underground Utilities & Drainage | C7: Site & Civil | D7: LOW | E7: =SUMIFS(Detail!$L$2:$L$868,Detail!$F$2:$F$868,$A7) | F7: =SUMIFS(Detail!$T$2:$T$868,Detail!$F$2:$F$868,$A7) | G7: =$E7+$F7 | H7: =COUNTIF(Detail!$F$2:$F$868,$A7)
A8: PKG-04 | B8: Pavement & Surfacing | C8: Site & Civil | D8: LOW | E8: =SUMIFS(Detail!$L$2:$L$868,Detail!$F$2:$F$868,$A8) | F8: =SUMIFS(Detail!$T$2:$T$868,Detail!$F$2:$F$868,$A8) | G8: =$E8+$F8 | H8: =COUNTIF(Detail!$F$2:$F$868,$A8)
A9: PKG-05 | B9: Concrete Structures | C9: Structural | D9: LOW | E9: =SUMIFS(Detail!$L$2:$L$868,Detail!$F$2:$F$868,$A9) | F9: =SUMIFS(Detail!$T$2:$T$868,Detail!$F$2:$F$868,$A9) | G9: =$E9+$F9 | H9: =COUNTIF(Detail!$F$2:$F$868,$A9)
A10: PKG-06 | B10: Structural Steelwork | C10: Structural | D10: LOW | E10: =SUMIFS(Detail!$L$2:$L$868,Detail!$F$2:$F$868,$A10) | F10: =SUMIFS(Detail!$T$2:$T$868,Detail!$F$2:$F$868,$A10) | G10: =$E10+$F10 | H10: =COUNTIF(Detail!$F$2:$F$868,$A10)
A11: PKG-07 | B11: Rail Works | C11: Structural | D11: LOW | E11: =SUMIFS(Detail!$L$2:$L$868,Detail!$F$2:$F$868,$A11) | F11: =SUMIFS(Detail!$T$2:$T$868,Detail!$F$2:$F$868,$A11) | G11: =$E11+$F11 | H11: =COUNTIF(Detail!$F$2:$F$868,$A11)
A12: PKG-08 | B12: Marine Structures | C12: Structural | D12: LOW | E12: =SUMIFS(Detail!$L$2:$L$868,Detail!$F$2:$F$868,$A12) | F12: =SUMIFS(Detail!$T$2:$T$868,Detail!$F$2:$F$868,$A12) | G12: =$E12+$F12 | H12: =COUNTIF(Detail!$F$2:$F$868,$A12)
A13: PKG-09 | B13: Marine Outfitting | C13: Structural | D13: LOW | E13: =SUMIFS(Detail!$L$2:$L$868,Detail!$F$2:$F$868,$A13) | F13: =SUMIFS(Detail!$T$2:$T$868,Detail!$F$2:$F$868,$A13) | G13: =$E13+$F13 | H13: =COUNTIF(Detail!$F$2:$F$868,$A13)
A14: PKG-10 | B14: Railcar Unloading System | C14: Mechanical | D14: LOW | E14: =SUMIFS(Detail!$L$2:$L$868,Detail!$F$2:$F$868,$A14) | F14: =SUMIFS(Detail!$T$2:$T$868,Detail!$F$2:$F$868,$A14) | G14: =$E14+$F14 | H14: =COUNTIF(Detail!$F$2:$F$868,$A14)
A15: PKG-11 | B15: Marine Loading System | C15: Mechanical | D15: LOW | E15: =SUMIFS(Detail!$L$2:$L$868,Detail!$F$2:$F$868,$A15) | F15: =SUMIFS(Detail!$T$2:$T$868,Detail!$F$2:$F$868,$A15) | G15: =$E15+$F15 | H15: =COUNTIF(Detail!$F$2:$F$868,$A15)
... A39: PKG-35 | B39: Training & Handover | C39: Project Execution | D39: LOW | E39: =SUMIFS(Detail!$L$2:$L$868,Detail!$F$2:$F$868,$A39) | F39: =SUMIFS(Detail!$T$2:$T$868,Detail!$F$2:$F$868,$A39) | G39: =$E39+$F39 | H39: =COUNTIF(Detail!$F$2:$F$868,$A39)

Sheet Summary_CBS
A1: CBS summary (computed from Detail) | H1: Home
A3: CBS | B3: Base | C3: Rate | D3: Contingency | E3: Total | F3: Share_of_Total
A4: MAT | B4: =SUMIFS(Detail!$L$2:$L$868,Detail!$E$2:$E$868,$A4) | C4: =VLOOKUP($A4,Inputs!$A$6:$B$13,2,FALSE)*Inputs!$B$2 | D4: =$B4*$C4 | E4: =$B4+$D4 | F4: =$E4/SUM($E$4:$E$11)
A5: CD | B5: =SUMIFS(Detail!$L$2:$L$868,Detail!$E$2:$E$868,$A5) | C5: =VLOOKUP($A5,Inputs!$A$6:$B$13,2,FALSE)*Inputs!$B$2 | D5: =$B5*$C5 | E5: =$B5+$D5 | F5: =$E5/SUM($E$4:$E$11)
A6: E | B6: =SUMIFS(Detail!$L$2:$L$868,Detail!$E$2:$E$868,$A6) | C6: =VLOOKUP($A6,Inputs!$A$6:$B$13,2,FALSE)*Inputs!$B$2 | D6: =$B6*$C6 | E6: =$B6+$D6 | F6: =$E6/SUM($E$4:$E$11)
A7: PM | B7: =SUMIFS(Detail!$L$2:$L$868,Detail!$E$2:$E$868,$A7) | C7: =VLOOKUP($A7,Inputs!$A$6:$B$13,2,FALSE)*Inputs!$B$2 | D7: =$B7*$C7 | E7: =$B7+$D7 | F7: =$E7/SUM($E$4:$E$11)
A8: CI | B8: =SUMIFS(Detail!$L$2:$L$868,Detail!$E$2:$E$868,$A8) | C8: =VLOOKUP($A8,Inputs!$A$6:$B$13,2,FALSE)*Inputs!$B$2 | D8: =$B8*$C8 | E8: =$B8+$D8 | F8: =$E8/SUM($E$4:$E$11)
A9: COM | B9: =SUMIFS(Detail!$L$2:$L$868,Detail!$E$2:$E$868,$A9) | C9: =VLOOKUP($A9,Inputs!$A$6:$B$13,2,FALSE)*Inputs!$B$2 | D9: =$B9*$C9 | E9: =$B9+$D9 | F9: =$E9/SUM($E$4:$E$11)
A10: P | B10: =SUMIFS(Detail!$L$2:$L$868,Detail!$E$2:$E$868,$A10) | C10: =VLOOKUP($A10,Inputs!$A$6:$B$13,2,FALSE)*Inputs!$B$2 | D10: =$B10*$C10 | E10: =$B10+$D10 | F10: =$E10/SUM($E$4:$E$11)
A11: FRT | B11: =SUMIFS(Detail!$L$2:$L$868,Detail!$E$2:$E$868,$A11) | C11: =VLOOKUP($A11,Inputs!$A$6:$B$13,2,FALSE)*Inputs!$B$2 | D11: =$B11*$C11 | E11: =$B11+$D11 | F11: =$E11/SUM($E$4:$E$11)
A12: TOTAL | B12: =SUM(B4:B11) | D12: =SUM(D4:D11) | E12: =SUM(E4:E11) | F12: 1

Sheet Summary_Methods
A1: Pricing method summary (computed from Detail) | G1: Home
A3: Method | B3: LineItems | C3: Base | D3: Share_of_Base
A4: ALLOWANCE | B4: =COUNTIF(Detail!$N$2:$N$868,$A4) | C4: =SUMIFS(Detail!$L$2:$L$868,Detail!$N$2:$N$868,$A4) | D4: =$C4/SUM($C$4:$C$7)
A5: CAD | B5: =COUNTIF(Detail!$N$2:$N$868,$A5) | C5: =SUMIFS(Detail!$L$2:$L$868,Detail!$N$2:$N$868,$A5) | D5: =$C5/SUM($C$4:$C$7)
A6: PARAMETRIC | B6: =COUNTIF(Detail!$N$2:$N$868,$A6) | C6: =SUMIFS(Detail!$L$2:$L$868,Detail!$N$2:$N$868,$A6) | D6: =$C6/SUM($C$4:$C$7)
A7: RATE_TABLE | B7: =COUNTIF(Detail!$N$2:$N$868,$A7) | C7: =SUMIFS(Detail!$L$2:$L$868,Detail!$N$2:$N$868,$A7) | D7: =$C7/SUM($C$4:$C$7)

Sheet Assumptions_Groups
A1: Assumptions — consolidated groups | I1: Home
A3: CategoryCode | B3: Category | C3: GroupID | D3: GroupTitle | E3: Theme | F3: PackagesCount | G3: Packages | H3: ItemsCount
A4: ASM-ENG | B4: Engineering Effort | C4: ASM-ENG-001 | D4: Design Calculations Effort | E4: Design Calculations Effort | F4: 8 | G4: PKG-05, PKG-06, PKG-08, PKG-10, PKG-11, PKG-17, PKG-20, PKG-21 | H4: 8
A5: ASM-ENG | B5: Engineering Effort | C5: ASM-ENG-002 | D5: Calculations | F5: 1 | G5: PKG-13 | H5: 1
A6: ASM-ENG | B6: Engineering Effort | C6: ASM-ENG-003 | D6: Design Codes and Standards | F6: 1 | G6: PKG-23 | H6: 1
A7: ASM-ENG | B7: Engineering Effort | C7: ASM-ENG-004 | D7: Drawings | F7: 1 | G7: PKG-13 | H7: 1
A8: ASM-ENG | B8: Engineering Effort | C8: ASM-ENG-005 | D8: Engineering Design Effort (6 Deliverables) | F8: 1 | G8: PKG-22 | H8: 1
A9: ASM-ENG | B9: Engineering Effort | C9: ASM-ENG-006 | D9: Engineering Drawing Effort | F9: 1 | G9: PKG-20 | H9: 1
A10: ASM-ENG | B10: Engineering Effort | C10: ASM-ENG-007 | D10: Engineering design at approximately 11% of construction value | F10: 1 | G10: PKG-21 | H10: 1
A11: ASM-ENG | B11: Engineering Effort | C11: ASM-ENG-008 | D11: Engineering effort estimated at **3,400 hours** across 5 deliverables | F11: 1 | G11: PKG-16 | H11: 1
A12: ASM-ENG | B12: Engineering Effort | C12: ASM-ENG-009 | D12: Lighting poles designed for NBCC 2020 seismic and wind loads for Surrey, BC loca... | F12: 1 | G12: PKG-18 | H12: 1
A13: ASM-ENG | B13: Engineering Effort | C13: ASM-ENG-010 | D13: Shop Drawings and Submittals | F13: 1 | G13: PKG-22 | H13: 1
A14: ASM-ENG | B14: Engineering Effort | C14: ASM-ENG-011 | D14: Specifications | F14: 1 | G14: PKG-13 | H14: 1
A15: ASM-ENG | B15: Engineering Effort | C15: ASM-ENG-012 | D15: Three HMI workstations: 2 operator stations + 1 engineering station | F15: 1 | G15: PKG-19 | H15: 1
A16: ASM-INTF | B16: Interface & Coordination | C16: ASM-INTF-013 | D16: Interface Dependencies | E16: Interface Dependencies | F16: 1 | G16: PKG-22 | H16: 4
A17: ASM-INTF | B17: Interface & Coordination | C17: ASM-INTF-014 | D17: PKG-27 A-2701 | F17: 4 | G17: PKG-27, PKG-28, PKG-29, PKG-30 | H17: 73
A18: ASM-INTF | B18: Interface & Coordination | C18: ASM-INTF-015 | D18: PKG-24 assumption A-001 - see source | F18: 2 | G18: PKG-24, PKG-25 | H18: 41
A19: ASM-INTF | B19: Interface & Coordination | C19: ASM-INTF-016 | D19: PKG-26 assumption A-2601 | F19: 1 | G19: PKG-26 | H19: 25
A20: ASM-INTF | B20: Interface & Coordination | C20: ASM-INTF-017 | D20: 40-60 HMI graphics screens for operator interface | F20: 1 | G20: PKG-19 | H20: 1
A21: ASM-INTF | B21: Interface & Coordination | C21: ASM-INTF-018 | D21: Control system equipment installed in MCC building per PKG-21/22 | F21: 1 | G21: PKG-19 | H21: 1
A22: ASM-INTF | B22: Interface & Coordination | C22: ASM-INTF-019 | D22: Coordination Meeting Records — DEL-34.01 | F22: 1 | G22: PKG-34 | H22: 1
A23: ASM-INTF | B23: Interface & Coordination | C23: ASM-INTF-020 | D23: Interface Agreements — DEL-34.02 | F23: 1 | G23: PKG-34 | H23: 1
A24: ASM-INTF | B24: Interface & Coordination | C24: ASM-INTF-021 | D24: Marine Coordination Records — DEL-34.03 | F24: 1 | G24: PKG-34 | H24: 1
A25: ASM-INTF | B25: Interface & Coordination | C25: ASM-INTF-022 | D25: Marine loading system (PKG-11) requires **~25 valves** (loading arm isolation, f... | F25: 1 | G25: PKG-16 | H25: 1
A26: ASM-INTF | B26: Interface & Coordination | C26: ASM-INTF-023 | D26: Product transfer and metering (PKG-12) requires **~30 valves** | F26: 1 | G26: PKG-16 | H26: 1
A27: ASM-INTF | B27: Interface & Coordination | C27: ASM-INTF-024 | D27: Site Access and Temporary Works (PKG-06 Allocation) | F27: 1 | G27: PKG-06 | H27: 1
A28: ASM-INTF | B28: Interface & Coordination | C28: ASM-INTF-025 | D28: Terminal Operations Coordination | F28: 1 | G28: PKG-23 | H28: 1
A29: ASM-LABOR | B29: Labor & Installation | C29: ASM-LABOR-026 | D29: Installation Labor Rates | E29: Installation Labor Rates | F29: 5 | G29: PKG-11, PKG-14, PKG-15, PKG-16, PKG-21 | H29: 11
A30: ASM-LABOR | B30: Labor & Installation | C30: ASM-LABOR-027 | D30: Actuator hookup (pneumatic/electrical) adds **2-4 hours per actuated valve** | F30: 1 | G30: PKG-16 | H30: 1
A31: ASM-LABOR | B31: Labor & Installation | C31: ASM-LABOR-028 | D31: Cable Tray and Conduit Installation Scope | F31: 1 | G31: PKG-17 | H31: 1
A32: ASM-LABOR | B32: Labor & Installation | C32: ASM-LABOR-029 | D32: Construction Labor Productivity | F32: 1 | G32: PKG-23 | H32: 1
A33: ASM-LABOR | B33: Labor & Installation | C33: ASM-LABOR-030 | D33: Construction Labor Rates (BC Lower Mainland) | F33: 1 | G33: PKG-22 | H33: 1
A34: ASM-LABOR | B34: Labor & Installation | C34: ASM-LABOR-031 | D34: Control valve calibration and loop check (30 valves) estimated at **4 hours per ... | F34: 1 | G34: PKG-16 | H34: 1
A35: ASM-LABOR | B35: Labor & Installation | C35: ASM-LABOR-032 | D35: Crane and Equipment for Steel Erection | F35: 1 | G35: PKG-06 | H35: 1
A36: ASM-LABOR | B36: Labor & Installation | C36: ASM-LABOR-033 | D36: Distribution Panel Installation Scope | F36: 1 | G36: PKG-17 | H36: 1
A37: ASM-LABOR | B37: Labor & Installation | C37: ASM-LABOR-034 | D37: Engineering Labor Hours | F37: 1 | G37: PKG-23 | H37: 1
A38: ASM-LABOR | B38: Labor & Installation | C38: ASM-LABOR-035 | D38: Fire Water Loop Installation Productivity | F38: 1 | G38: PKG-23 | H38: 1
A39: ASM-LABOR | B39: Labor & Installation | C39: ASM-LABOR-036 | D39: Grating Supply and Installation | F39: 1 | G39: PKG-06 | H39: 1
A40: ASM-LABOR | B40: Labor & Installation | C40: ASM-LABOR-037 | D40: Grounding System Installation Scope | F40: 1 | G40: PKG-17 | H40: 1
A41: ASM-LABOR | B41: Labor & Installation | C41: ASM-LABOR-038 | D41: Handrail Supply and Installation | F41: 1 | G41: PKG-06 | H41: 1
... A56: ASM-LABOR | B56: Labor & Installation | C56: ASM-LABOR-053 | D56: Valve installation includes rigging, bolting, gasket installation, alignment, hy... | F56: 1 | G56: PKG-16 | H56: 1
A57: ASM-PRICE | B57: Pricing Allowances | C57: ASM-PRICE-054 | D57: Material Quantities | E57: Material Quantities | F57: 8 | G57: PKG-05, PKG-10, PKG-11, PKG-14, PKG-15, PKG-16, PKG-18, PKG-21 | H57: 40
A58: ASM-PRICE | B58: Pricing Allowances | C58: ASM-PRICE-055 | D58: Equipment Unit Pricing | E58: Equipment Unit Pricing | F58: 5 | G58: PKG-10, PKG-11, PKG-14, PKG-16, PKG-18 | H58: 36
A59: ASM-PRICE | B59: Pricing Allowances | C59: ASM-PRICE-056 | D59: Technical Specification Writing | E59: Technical Specification Writing | F59: 14 | G59: PKG-00, PKG-01, PKG-05, PKG-06, PKG-08, PKG-10, PKG-11, PKG-14, PKG-16, PKG-17, PKG-19, PKG-20, PKG-21, PKG-32 | H59: 16
A60: ASM-PRICE | B60: Pricing Allowances | C60: ASM-PRICE-057 | D60: Engineering Drawing Production | E60: Engineering Drawing Production | F60: 11 | G60: PKG-00, PKG-01, PKG-05, PKG-06, PKG-08, PKG-10, PKG-11, PKG-14, PKG-17, PKG-19, PKG-21 | H60: 12
A61: ASM-PRICE | B61: Pricing Allowances | C61: ASM-PRICE-058 | D61: Installation & Test Records | E61: Installation & Test Records | F61: 9 | G61: PKG-05, PKG-06, PKG-08, PKG-10, PKG-11, PKG-13, PKG-14, PKG-17, PKG-20 | H61: 9
A62: ASM-PRICE | B62: Pricing Allowances | C62: ASM-PRICE-059 | D62: Data Sheet Package | E62: Data Sheet Package | F62: 6 | G62: PKG-06, PKG-10, PKG-11, PKG-17, PKG-19, PKG-21 | H62: 6
A63: ASM-PRICE | B63: Pricing Allowances | C63: ASM-PRICE-060 | D63: 32 individual spill containment pans (one per unloading station) at $8,000/unit. | F63: 1 | G63: PKG-10 | H63: 1
A64: ASM-PRICE | B64: Pricing Allowances | C64: ASM-PRICE-061 | D64: 7 doors (6 personnel + 1 overhead) at $4,500 average | F64: 1 | G64: PKG-21 | H64: 1
A65: ASM-PRICE | B65: Pricing Allowances | C65: ASM-PRICE-062 | D65: API 610 process pump costs estimated as follows: | F65: 1 | G65: PKG-15 | H65: 1
A66: ASM-PRICE | B66: Pricing Allowances | C66: ASM-PRICE-063 | D66: Abutment Materials Allowance | F66: 1 | G66: PKG-08 | H66: 1
A67: ASM-PRICE | B67: Pricing Allowances | C67: ASM-PRICE-064 | D67: Actuator costs: Pneumatic $3k-$15k (size-dependent), Electric $8k-$40k (size-dep... | F67: 1 | G67: PKG-16 | H67: 1
A68: ASM-PRICE | B68: Pricing Allowances | C68: ASM-PRICE-065 | D68: Building Size for MEP Allowance Scaling | F68: 1 | G68: PKG-22 | H68: 1
A69: ASM-PRICE | B69: Pricing Allowances | C69: ASM-PRICE-066 | D69: Building commissioning coordination at $15,000 | F69: 1 | G69: PKG-21 | H69: 1
A70: ASM-PRICE | B70: Pricing Allowances | C70: ASM-PRICE-067 | D70: CEMP Compliance Monitoring Allowance | F70: 1 | G70: PKG-33 | H70: 1
A71: ASM-PRICE | B71: Pricing Allowances | C71: ASM-PRICE-068 | D71: Catwalk Structural Steel Supply Allowance | F71: 1 | G71: PKG-08 | H71: 1
A72: ASM-PRICE | B72: Pricing Allowances | C72: ASM-PRICE-069 | D72: Catwalk and Abutment Installation Allowance | F72: 1 | G72: PKG-08 | H72: 1
A73: ASM-PRICE | B73: Pricing Allowances | C73: ASM-PRICE-070 | D73: Commissioning Parametric Allowance | F73: 1 | G73: PKG-32 | H73: 1
A74: ASM-PRICE | B74: Pricing Allowances | C74: ASM-PRICE-071 | D74: Concrete testing and quality control services estimated at $65,000 CAD allowance... | F74: 1 | G74: PKG-05 | H74: 1
... A196: ASM-QTY | B196: Quantity Assumptions | C196: ASM-QTY-193 | D196: Valve count by type: 30 control (13%), 150 isolation (68%), 20 relief (9%), 20 s... | F196: 1 | G196: PKG-16 | H196: 1
A197: ASM-SCOPE | B197: Scope Boundaries | C197: ASM-SCOPE-194 | D197: Construction Indirects Factor | E197: Construction Indirects Factor | F197: 3 | G197: PKG-14, PKG-15, PKG-16 | H197: 3
A198: ASM-SCOPE | B198: Scope Boundaries | C198: ASM-SCOPE-195 | D198: Scope Exclusions | E198: Scope Exclusions | F198: 1 | G198: PKG-16 | H198: 2
A199: ASM-SCOPE | B199: Scope Boundaries | C199: ASM-SCOPE-196 | D199: Cable Pulling and Termination Scope | F199: 1 | G199: PKG-17 | H199: 1
A200: ASM-SCOPE | B200: Scope Boundaries | C200: ASM-SCOPE-197 | D200: Electrical Testing and Commissioning Support Scope | F200: 1 | G200: PKG-17 | H200: 1
A201: ASM-SCOPE | B201: Scope Boundaries | C201: ASM-SCOPE-198 | D201: Fire Water Loop Piping Scope | F201: 1 | G201: PKG-23 | H201: 1
A202: ASM-SCOPE | B202: Scope Boundaries | C202: ASM-SCOPE-199 | D202: Grounding System Scope | F202: 1 | G202: PKG-17 | H202: 1
A203: ASM-SCOPE | B203: Scope Boundaries | C203: ASM-SCOPE-200 | D203: Lighting controls include occupancy sensing, daylight harvesting, and time sched... | F203: 1 | G203: PKG-18 | H203: 1
A204: ASM-SCOPE | B204: Scope Boundaries | C204: ASM-SCOPE-201 | D204: Phase 2 connection provisions included in DEL-14.01 scope | F204: 1 | G204: PKG-14 | H204: 1
A205: ASM-SCOPE | B205: Scope Boundaries | C205: ASM-SCOPE-202 | D205: Testing and Commissioning Scope | F205: 1 | G205: PKG-22 | H205: 1
A206: ASM-SCOPE | B206: Scope Boundaries | C206: ASM-SCOPE-203 | D206: Valve testing (DEL-16.05) included in **COM factor** (no separate testing line) | F206: 1 | G206: PKG-16 | H206: 1
A207: ASM-TECH | B207: Technical Parameters | C207: ASM-TECH-204 | D207: Material Specification | E207: Material Specification | F207: 4 | G207: PKG-11, PKG-14, PKG-16, PKG-18 | H207: 5
A208: ASM-TECH | B208: Technical Parameters | C208: ASM-TECH-205 | D208: Contingency Percentage | E208: Contingency Percentage | F208: 1 | G208: PKG-01 | H208: 1
A209: ASM-TECH | B209: Technical Parameters | C209: ASM-TECH-206 | D209: All valves comply with **API/ASME/CSA standards** (premium quality; not economy-... | F209: 1 | G209: PKG-16 | H209: 1
A210: ASM-TECH | B210: Technical Parameters | C210: ASM-TECH-207 | D210: Fire Water and Fire Alarm Material Pricing | F210: 1 | G210: PKG-23 | H210: 1
A211: ASM-TECH | B211: Technical Parameters | C211: ASM-TECH-208 | D211: Foam System Material Pricing | F211: 1 | G211: PKG-23 | H211: 1
A212: ASM-TECH | B212: Technical Parameters | C212: ASM-TECH-209 | D212: Gaskets, bolting, small fittings at ~5% of pipe material | F212: 1 | G212: PKG-14 | H212: 1
A213: ASM-TECH | B213: Technical Parameters | C213: ASM-TECH-210 | D213: HVAC System Capacity and Equipment | F213: 1 | G213: PKG-22 | H213: 1
A214: ASM-TECH | B214: Technical Parameters | C214: ASM-TECH-211 | D214: Instrument Environment Rating | F214: 1 | G214: PKG-20 | H214: 1
A215: ASM-TECH | B215: Technical Parameters | C215: ASM-TECH-212 | D215: Interior process/warehouse area fixtures require IP54+ rating for dust and moist... | F215: 1 | G215: PKG-18 | H215: 1
A216: ASM-TECH | B216: Technical Parameters | C216: ASM-TECH-213 | D216: Plumbing Piping Materials and Routing | F216: 1 | G216: PKG-22 | H216: 1
A217: ASM-TECH | B217: Technical Parameters | C217: ASM-TECH-214 | D217: Structural Steel Material Supply (Fabricated Tonnage) | F217: 1 | G217: PKG-06 | H217: 1
A218: ASM-TECH | B218: Technical Parameters | C218: ASM-TECH-215 | D218: Valve materials and coatings suitable for **C4/C5-M corrosion category** (coasta... | F218: 1 | G218: PKG-16 | H218: 1
A219: UNCATEGORIZED | B219: Uncategorized | C219: UNCATEGORIZED-216 | D219: Weather/Season Impact | E219: Weather/Season Impact | F219: 2 | G219: PKG-10, PKG-11 | H219: 2
A220: UNCATEGORIZED | B220: Uncategorized | C220: UNCATEGORIZED-217 | D220: 40-50 I/O modules to support 600-800 I/O points | F220: 1 | G220: PKG-19 | H220: 1
A221: UNCATEGORIZED | B221: Uncategorized | C221: UNCATEGORIZED-218 | D221: 6-8 control cabinets (main panels + field junction boxes) | F221: 1 | G221: PKG-19 | H221: 1
A222: UNCATEGORIZED | B222: Uncategorized | C222: UNCATEGORIZED-219 | D222: 8 sump pumps for grouped containment drainage (4 pumps per zone × 2 zones). | F222: 1 | G222: PKG-10 | H222: 1
A223: UNCATEGORIZED | B223: Uncategorized | C223: UNCATEGORIZED-220 | D223: 8-10 industrial network switches for control network | F223: 1 | G223: PKG-19 | H223: 1
A224: UNCATEGORIZED | B224: Uncategorized | C224: UNCATEGORIZED-221 | D224: Access equip | F224: 1 | G224: PKG-13 | H224: 1
A225: UNCATEGORIZED | B225: Uncategorized | C225: UNCATEGORIZED-222 | D225: Actuators and accessories rated for **Class I, Division 2 / Zone 2** (Group D) h... | F225: 1 | G225: PKG-16 | H225: 1
A226: UNCATEGORIZED | B226: Uncategorized | C226: UNCATEGORIZED-223 | D226: Agitators | F226: 1 | G226: PKG-13 | H226: 1
A227: UNCATEGORIZED | B227: Uncategorized | C227: UNCATEGORIZED-224 | D227: Basic Process Control System (BPCS) only; no separate SIS | F227: 1 | G227: PKG-19 | H227: 1
A228: UNCATEGORIZED | B228: Uncategorized | C228: UNCATEGORIZED-225 | D228: Cable Routing Method | F228: 1 | G228: PKG-20 | H228: 1
A229: UNCATEGORIZED | B229: Uncategorized | C229: UNCATEGORIZED-226 | D229: Cable Tray Length and Type | F229: 1 | G229: PKG-17 | H229: 1
A230: UNCATEGORIZED | B230: Uncategorized | C230: UNCATEGORIZED-227 | D230: Calibration and Loop Testing | F230: 1 | G230: PKG-20 | H230: 1
A231: UNCATEGORIZED | B231: Uncategorized | C231: UNCATEGORIZED-228 | D231: Canola oil properties assumed as: | F231: 1 | G231: PKG-15 | H231: 1
... A314: UNCATEGORIZED | B314: Uncategorized | C314: UNCATEGORIZED-311 | D314: Weld Inspection and NDT | F314: 1 | G314: PKG-06 | H314: 1

Sheet Assumptions_Items
A1: Assumptions — source items | H1: Home
A3: CategoryCode | B3: Category | C3: GroupID | D3: GroupTitle | E3: Package | F3: AssumptionID | G3: Description
A4: ASM-ENG | B4: Engineering Effort | C4: ASM-ENG-001 | D4: Design Calculations Effort | E4: PKG-05 | F4: A-003 | G4: Concrete structures design calculations (foundation calcs,..
A5: ASM-ENG | B5: Engineering Effort | C5: ASM-ENG-001 | D5: Design Calculations Effort | E5: PKG-06 | F5: A-003 | G5: Structural Steel Design Calculations Effort
A6: ASM-ENG | B6: Engineering Effort | C6: ASM-ENG-001 | D6: Design Calculations Effort | E6: PKG-08 | F6: A-803 | G6: DEL-08.03 Design Calculations Allowance
A7: ASM-ENG | B7: Engineering Effort | C7: ASM-ENG-001 | D7: Design Calculations Effort | E7: PKG-10 | F7: A-008 | G7: DEL-10.03 Design Calculations engineering effort priced at..
A8: ASM-ENG | B8: Engineering Effort | C8: ASM-ENG-001 | D8: Design Calculations Effort | E8: PKG-11 | F8: A-009 | G8: Design calculations require ~80 hours at $250/hr (senior p..
A9: ASM-ENG | B9: Engineering Effort | C9: ASM-ENG-001 | D9: Design Calculations Effort | E9: PKG-17 | F9: A-1703 | G9: Electrical Power Design Calculations Allowance
A10: ASM-ENG | B10: Engineering Effort | C10: ASM-ENG-001 | D10: Design Calculations Effort | E10: PKG-20 | F10: A-013 | G10: Design Calculation Effort
A11: ASM-ENG | B11: Engineering Effort | C11: ASM-ENG-001 | D11: Design Calculations Effort | E11: PKG-21 | F11: A-005 | G11: Structural/foundation calculations at $45,000 allowance
A12: ASM-ENG | B12: Engineering Effort | C12: ASM-ENG-002 | D12: Calculations | E12: PKG-13 | F12: A-013 | G12: Calculations
A13: ASM-ENG | B13: Engineering Effort | C13: ASM-ENG-003 | D13: Design Codes and Standards | E13: PKG-23 | F13: A-022 | G13: Design Codes and Standards
A14: ASM-ENG | B14: Engineering Effort | C14: ASM-ENG-004 | D14: Drawings | E14: PKG-13 | F14: A-011 | G14: Drawings
... A591: UNCATEGORIZED | B591: Uncategorized | C591: UNCATEGORIZED-311 | D591: Weld Inspection and NDT | E591: PKG-06 | F591: A-015 | G591: Weld Inspection and NDT

Sheet Risks_Groups
A1: Risks — consolidated groups | I1: Home
A3: CategoryCode | B3: Category | C3: GroupID | D3: GroupTitle | E3: Theme | F3: PackagesCount | G3: Packages | H3: ItemsCount
A4: RSK-ENV | B4: Environmental Risk | C4: RSK-ENV-001 | D4: Weather/Environmental Risk | E4: Weather/Environmental Risk | F4: 9 | G4: PKG-01, PKG-08, PKG-11, PKG-13, PKG-14, PKG-16, PKG-20, PKG-21, PKG-23 | H4: 10
A5: RSK-ENV | B5: Environmental Risk | C5: RSK-ENV-002 | D5: Marine Logistics Constraints | F5: 1 | G5: PKG-08 | H5: 1
A6: RSK-ESC | B6: Escalation Risk | C6: RSK-ESC-003 | D6: Cost Escalation Exposure | E6: Cost Escalation Exposure | F6: 11 | G6: PKG-00, PKG-05, PKG-15, PKG-16, PKG-22, PKG-23, PKG-31, PKG-32, PKG-33, PKG-34, PKG-35 | H6: 14
A7: RSK-INTF | B7: Interface Risk | C7: RSK-INTF-004 | D7: Interface & Coordination Risk | E7: Interface & Coordination Risk | F7: 9 | G7: PKG-00, PKG-05, PKG-10, PKG-11, PKG-14, PKG-16, PKG-22, PKG-32, PKG-34 | H7: 16
A8: RSK-INTF | B8: Interface Risk | C8: RSK-INTF-005 | D8: PKG-27 R-2701 | F8: 4 | G8: PKG-27, PKG-28, PKG-29, PKG-30 | H8: 38
A9: RSK-INTF | B9: Interface Risk | C9: RSK-INTF-006 | D9: PKG-24 risk R-001 - see source | F9: 2 | G9: PKG-24, PKG-25 | H9: 18
A10: RSK-INTF | B10: Interface Risk | C10: RSK-INTF-007 | D10: PKG-26 risk R-2601 | F10: 1 | G10: PKG-26 | H10: 8
A11: RSK-INTF | B11: Interface Risk | C11: RSK-INTF-008 | D11: Control Room Integration | F11: 1 | G11: PKG-19 | H11: 1
A12: RSK-INTF | B12: Interface Risk | C12: RSK-INTF-009 | D12: Coordination and Interface Delays | F12: 1 | G12: PKG-15 | H12: 1
A13: RSK-INTF | B13: Interface Risk | C13: RSK-INTF-010 | D13: Emergency Response Plan Integration Complexity | F13: 1 | G13: PKG-33 | H13: 1
A14: RSK-INTF | B14: Interface Risk | C14: RSK-INTF-011 | D14: Integration with Control System | F14: 1 | G14: PKG-15 | H14: 1
A15: RSK-INTF | B15: Interface Risk | C15: RSK-INTF-012 | D15: Integration with Existing Terminal Systems | F15: 1 | G15: PKG-19 | H15: 1
A16: RSK-INTF | B16: Interface Risk | C16: RSK-INTF-013 | D16: Interface - Marine Access | F16: 1 | G16: PKG-11 | H16: 1
A17: RSK-INTF | B17: Interface Risk | C17: RSK-INTF-014 | D17: Interface with Other Packages (HSE Dependencies) | F17: 1 | G17: PKG-33 | H17: 1
A18: RSK-INTF | B18: Interface Risk | C18: RSK-INTF-015 | D18: Loop Testing Coordination | F18: 1 | G18: PKG-20 | H18: 1
A19: RSK-INTF | B19: Interface Risk | C19: RSK-INTF-016 | D19: Marine Coordination Complexity | F19: 1 | G19: PKG-34 | H19: 1
... A21: RSK-INTF | B21: Interface Risk | C21: RSK-INTF-018 | D21: Site Access and Operational Interface Risk | F21: 1 | G21: PKG-16 | H21: 1
A22: RSK-PRICE | B22: Price Uncertainty | C22: RSK-PRICE-019 | D22: No Vendor Pricing/Quotes Available | E22: No Vendor Pricing/Quotes Available | F22: 9 | G22: PKG-00, PKG-01, PKG-05, PKG-10, PKG-11, PKG-14, PKG-15, PKG-16, PKG-34 | H22: 9
A23: RSK-PRICE | B23: Price Uncertainty | C23: RSK-PRICE-020 | D23: Control System Vendor Selection | F23: 1 | G23: PKG-19 | H23: 1
A24: RSK-PRICE | B24: Price Uncertainty | C24: RSK-PRICE-021 | D24: Equipment - Loading Arm Pricing | F24: 1 | G24: PKG-11 | H24: 1
A25: RSK-PRICE | B25: Price Uncertainty | C25: RSK-PRICE-022 | D25: Marine Contractor Availability and Pricing Volatility | F25: 1 | G25: PKG-08 | H25: 1
A26: RSK-PRICE | B26: Price Uncertainty | C26: RSK-PRICE-023 | D26: Steel price volatility | F26: 1 | G26: PKG-13 | H26: 1
A27: RSK-PRICE | B27: Price Uncertainty | C27: RSK-PRICE-024 | D27: Vendor FAT Location | F27: 1 | G27: PKG-19 | H27: 1
A28: RSK-PRICE | B28: Price Uncertainty | C28: RSK-PRICE-025 | D28: Vendor Quote Unavailability | F28: 1 | G28: PKG-22 | H28: 1
A29: RSK-PROD | B29: Productivity Risk | C29: RSK-PROD-026 | D29: Labor Availability & Productivity | E29: Labor Availability & Productivity | F29: 6 | G29: PKG-05, PKG-10, PKG-15, PKG-16, PKG-21, PKG-22 | H29: 7
A30: RSK-PROD | B30: Productivity Risk | C30: RSK-PROD-027 | D30: Site Access During Operations | F30: 1 | G30: PKG-20 | H30: 1
A31: RSK-QTY | B31: Quantity Risk | C31: RSK-QTY-028 | D31: Quantity Uncertainty | E31: Quantity Uncertainty | F31: 5 | G31: PKG-05, PKG-15, PKG-16, PKG-20, PKG-33 | H31: 5
A32: RSK-QTY | B32: Quantity Risk | C32: RSK-QTY-029 | D32: Actuator Sizing and Safety Factor Risk | F32: 1 | G32: PKG-16 | H32: 1
A33: RSK-QTY | B33: Quantity Risk | C33: RSK-QTY-030 | D33: Method Statement and Risk Assessment Volume | F33: 1 | G33: PKG-33 | H33: 1
A34: RSK-QUAL | B34: Quality Risk | C34: RSK-QUAL-031 | D34: Quality/Rework Risk | E34: Quality/Rework Risk | F34: 6 | G34: PKG-11, PKG-13, PKG-14, PKG-15, PKG-31, PKG-35 | H34: 6
A35: RSK-QUAL | B35: Quality Risk | C35: RSK-QUAL-032 | D35: Engineering Effort Underestimated (LOW) | F35: 1 | G35: PKG-01 | H35: 1
A36: RSK-QUAL | B36: Quality Risk | C36: RSK-QUAL-033 | D36: NDE findings | F36: 1 | G36: PKG-13 | H36: 1
A37: RSK-QUAL | B37: Quality Risk | C37: RSK-QUAL-034 | D37: Underground Utility Conflicts | F37: 1 | G37: PKG-23 | H37: 1
A38: RSK-REG | B38: Regulatory Risk | C38: RSK-REG-035 | D38: Regulatory/Permitting Risk | E38: Regulatory/Permitting Risk | F38: 9 | G38: PKG-00, PKG-08, PKG-10, PKG-11, PKG-15, PKG-21, PKG-23, PKG-32, PKG-33 | H38: 10
A39: RSK-SCHED | B39: Schedule Risk | C39: RSK-SCHED-036 | D39: Schedule/Lead Time Risk | E39: Schedule/Lead Time Risk | F39: 11 | G39: PKG-00, PKG-08, PKG-11, PKG-14, PKG-15, PKG-16, PKG-18, PKG-20, PKG-21, PKG-23, PKG-35 | H39: 11
A40: RSK-SCHED | B40: Schedule Risk | C40: RSK-SCHED-037 | D40: Construction Schedule Duration Variance | F40: 1 | G40: PKG-33 | H40: 1
A41: RSK-SCHED | B41: Schedule Risk | C41: RSK-SCHED-038 | D41: Employer Staffing Delays (LOW) | F41: 1 | G41: PKG-35 | H41: 1
A42: RSK-SCHED | B42: Schedule Risk | C42: RSK-SCHED-039 | D42: Project Duration Extension | F42: 1 | G42: PKG-34 | H42: 1
A43: RSK-SCOPE | B43: Scope Risk | C43: RSK-SCOPE-040 | D43: Scope Definition/Growth Risk | E43: Scope Definition/Growth Risk | F43: 8 | G43: PKG-00, PKG-01, PKG-13, PKG-15, PKG-16, PKG-22, PKG-32, PKG-33 | H43: 12
A44: RSK-SCOPE | B44: Scope Risk | C44: RSK-SCOPE-041 | D44: Technical Design Complexity | E44: Technical Design Complexity | F44: 6 | G44: PKG-05, PKG-08, PKG-13, PKG-14, PKG-18, PKG-21 | H44: 7
A45: RSK-SCOPE | B45: Scope Risk | C45: RSK-SCOPE-042 | D45: Control System Integration | E45: Control System Integration | F45: 3 | G45: PKG-18, PKG-19, PKG-20 | H45: 6
A46: RSK-SCOPE | B46: Scope Risk | C46: RSK-SCOPE-043 | D46: Commissioning/Testing Complexity | E46: Commissioning/Testing Complexity | F46: 5 | G46: PKG-10, PKG-11, PKG-15, PKG-16, PKG-22 | H46: 5
A47: RSK-SCOPE | B47: Scope Risk | C47: RSK-SCOPE-044 | D47: Equipment Specification Risk | E47: Equipment Specification Risk | F47: 1 | G47: PKG-15 | H47: 1
A48: RSK-SCOPE | B48: Scope Risk | C48: RSK-SCOPE-045 | D48: API 610 Compliance Requirement Interpretation | F48: 1 | G48: PKG-15 | H48: 1
A49: RSK-SCOPE | B49: Scope Risk | C49: RSK-SCOPE-046 | D49: Actuator and Automation Requirements Risk | F49: 1 | G49: PKG-16 | H49: 1
A50: RSK-SCOPE | B50: Scope Risk | C50: RSK-SCOPE-047 | D50: Asset Hierarchy / CMMS Requirements Complexity | F50: 1 | G50: PKG-31 | H50: 1
A51: RSK-SCOPE | B51: Scope Risk | C51: RSK-SCOPE-048 | D51: Canola Oil Fluid Properties and Heating Requirements | F51: 1 | G51: PKG-15 | H51: 1
A52: RSK-SCOPE | B52: Scope Risk | C52: RSK-SCOPE-049 | D52: Containment Performance Requirements | F52: 1 | G52: PKG-05 | H52: 1
A53: RSK-SCOPE | B53: Scope Risk | C53: RSK-SCOPE-050 | D53: ER Illumination Requirements Exceed Typical Standards | F53: 1 | G53: PKG-18 | H53: 1
A54: RSK-SCOPE | B54: Scope Risk | C54: RSK-SCOPE-051 | D54: Employer's Requirements Interpretation Risk | F54: 1 | G54: PKG-32 | H54: 1
A55: RSK-SCOPE | B55: Scope Risk | C55: RSK-SCOPE-052 | D55: Employer's Requirements Not Extracted | F55: 1 | G55: PKG-05 | H55: 1
A56: RSK-SCOPE | B56: Scope Risk | C56: RSK-SCOPE-053 | D56: Food-Grade Material Requirements | F56: 1 | G56: PKG-15 | H56: 1
A57: RSK-SCOPE | B57: Scope Risk | C57: RSK-SCOPE-054 | D57: Food-Grade Material Requirements Risk | F57: 1 | G57: PKG-10 | H57: 1
A58: RSK-SCOPE | B58: Scope Risk | C58: RSK-SCOPE-055 | D58: Language/Translation Requirements (LOW) | F58: 1 | G58: PKG-35 | H58: 1
A59: RSK-SCOPE | B59: Scope Risk | C59: RSK-SCOPE-056 | D59: Plumbing Fixture Count and Hot Water Requirements | F59: 1 | G59: PKG-22 | H59: 1
... A69: RSK-SCOPE | B69: Scope Risk | C69: RSK-SCOPE-066 | D69: Trenchless Crossing Monitoring Scope | F69: 1 | G69: PKG-34 | H69: 1
A70: RSK-TECH | B70: Technical Risk | C70: RSK-TECH-067 | D70: Geotechnical/Foundation Risk | E70: Geotechnical/Foundation Risk | F70: 4 | G70: PKG-05, PKG-08, PKG-13, PKG-21 | H70: 6
A71: RSK-TECH | B71: Technical Risk | C71: RSK-TECH-068 | D71: As-Built Markup Complexity | F71: 1 | G71: PKG-31 | H71: 1
A72: RSK-TECH | B72: Technical Risk | C72: RSK-TECH-069 | D72: Control Valve Complexity and Trim Selection Risk | F72: 1 | G72: PKG-16 | H72: 1
A73: RSK-TECH | B73: Technical Risk | C73: RSK-TECH-070 | D73: Network Infrastructure Complexity | F73: 1 | G73: PKG-19 | H73: 1
A74: RSK-TECH | B74: Technical Risk | C74: RSK-TECH-071 | D74: Salt Tent Structure Complexity Unknown (LOW) | F74: 1 | G74: PKG-01 | H74: 1
A75: RSK-TECH | B75: Technical Risk | C75: RSK-TECH-072 | D75: Seal System Complexity | F75: 1 | G75: PKG-15 | H75: 1
A76: RSK-TECH | B76: Technical Risk | C76: RSK-TECH-073 | D76: Technical - Expansion Provisions | F76: 1 | G76: PKG-14 | H76: 1
A77: RSK-TECH | B77: Technical Risk | C77: RSK-TECH-074 | D77: Technical - Vessel Envelope | F77: 1 | G77: PKG-11 | H77: 1
A78: UNCATEGORIZED | B78: Uncategorized | C78: UNCATEGORIZED-075 | D78: Fire Protection Requirements | E78: Fire Protection Requirements | F78: 1 | G78: PKG-23 | H78: 4
A79: UNCATEGORIZED | B79: Uncategorized | C79: UNCATEGORIZED-076 | D79: Hazardous Area Classification | E79: Hazardous Area Classification | F79: 4 | G79: PKG-16, PKG-18, PKG-20, PKG-21 | H79: 4
A80: UNCATEGORIZED | B80: Uncategorized | C80: UNCATEGORIZED-077 | D80: Installation/Construction Complexity | E80: Installation/Construction Complexity | F80: 1 | G80: PKG-15 | H80: 1
A81: UNCATEGORIZED | B81: Uncategorized | C81: UNCATEGORIZED-078 | D81: Agitator selection | F81: 1 | G81: PKG-13 | H81: 1
A82: UNCATEGORIZED | B82: Uncategorized | C82: UNCATEGORIZED-079 | D82: Building Configuration Changes Affecting Interior Lighting | F82: 1 | G82: PKG-18 | H82: 1
A83: UNCATEGORIZED | B83: Uncategorized | C83: UNCATEGORIZED-080 | D83: Building Size Uncertainty | F83: 1 | G83: PKG-22 | H83: 1
A84: UNCATEGORIZED | B84: Uncategorized | C84: UNCATEGORIZED-081 | D84: Cable Routing and Length Uncertainty | F84: 1 | G84: PKG-20 | H84: 1
A85: UNCATEGORIZED | B85: Uncategorized | C85: UNCATEGORIZED-082 | D85: Calibration Equipment Availability | F85: 1 | G85: PKG-20 | H85: 1
A86: UNCATEGORIZED | B86: Uncategorized | C86: UNCATEGORIZED-083 | D86: Canola Oil Product Compatibility | F86: 1 | G86: PKG-20 | H86: 1
A87: UNCATEGORIZED | B87: Uncategorized | C87: UNCATEGORIZED-084 | D87: Commissioning - Flushing | F87: 1 | G87: PKG-14 | H87: 1
A88: UNCATEGORIZED | B88: Uncategorized | C88: UNCATEGORIZED-085 | D88: Containment Configuration Uncertainty | F88: 1 | G88: PKG-10 | H88: 1
A89: UNCATEGORIZED | B89: Uncategorized | C89: UNCATEGORIZED-086 | D89: Control Valve Positioner and Communication Protocol Risk | F89: 1 | G89: PKG-16 | H89: 1
A90: UNCATEGORIZED | B90: Uncategorized | C90: UNCATEGORIZED-087 | D90: Disposal Facility Capacity/Cost Changes (MEDIUM) | F90: 1 | G90: PKG-01 | H90: 1
A91: UNCATEGORIZED | B91: Uncategorized | C91: UNCATEGORIZED-088 | D91: Documentation Completeness (LOW) | F91: 1 | G91: PKG-35 | H91: 1
A92: UNCATEGORIZED | B92: Uncategorized | C92: UNCATEGORIZED-089 | D92: Drawing Count Variance | F92: 1 | G92: PKG-31 | H92: 1
... A123: UNCATEGORIZED | B123: Uncategorized | C123: UNCATEGORIZED-120 | D123: Valve Size and Specification Risk | F123: 1 | G123: PKG-16 | H123: 1

Sheet Risks_Items
A1: Risks — source items | I1: Home
A3: CategoryCode | B3: Category | C3: GroupID | D3: GroupTitle | E3: Package | F3: RiskID | G3: RiskTitle | H3: Severity
A4: RSK-ENV | B4: Environmental Risk | C4: RSK-ENV-001 | D4: Weather/Environmental Risk | E4: PKG-01 | F4: R-104 | G4: Marine Weather/Tide Delays (MEDIUM) | H4: MEDIUM
A5: RSK-ENV | B5: Environmental Risk | C5: RSK-ENV-001 | D5: Weather/Environmental Risk | E5: PKG-08 | F5: R-805 | G5: Environmental Design Basis More Severe Than Assumed
A6: RSK-ENV | B6: Environmental Risk | C6: RSK-ENV-001 | D6: Weather/Environmental Risk | E6: PKG-11 | F6: R-011 | G6: Environmental - Weather
A7: RSK-ENV | B7: Environmental Risk | C7: RSK-ENV-001 | D7: Weather/Environmental Risk | E7: PKG-13 | F7: R-008 | G7: Weather impacts
A8: RSK-ENV | B8: Environmental Risk | C8: RSK-ENV-001 | D8: Weather/Environmental Risk | E8: PKG-14 | F8: R-016 | G8: Environmental - Material Storage
A9: RSK-ENV | B9: Environmental Risk | C9: RSK-ENV-001 | D9: Weather/Environmental Risk | E9: PKG-16 | F9: R-1620 | G9: Winter Construction Productivity Impact
A10: RSK-ENV | B10: Environmental Risk | C10: RSK-ENV-001 | D10: Weather/Environmental Risk | E10: PKG-20 | F10: R-006 | G10: Marine Environment Corrosion
A11: RSK-ENV | B11: Environmental Risk | C11: RSK-ENV-001 | D11: Weather/Environmental Risk | E11: PKG-20 | F11: R-012 | G11: Winter Weather Impact
A12: RSK-ENV | B12: Environmental Risk | C12: RSK-ENV-001 | D12: Weather/Environmental Risk | E12: PKG-21 | F12: R-004 | G12: Marine Environment Corrosion Protection
A13: RSK-ENV | B13: Environmental Risk | C13: RSK-ENV-001 | D13: Weather/Environmental Risk | E13: PKG-23 | F13: R-010 | G13: Marine Environment Corrosion
A14: RSK-ENV | B14: Environmental Risk | C14: RSK-ENV-002 | D14: Marine Logistics Constraints | E14: PKG-08 | F14: R-802 | G14: Marine Logistics Constraints
A15: RSK-ESC | B15: Escalation Risk | C15: RSK-ESC-003 | D15: Cost Escalation Exposure | E15: PKG-00 | F15: R-008 | G15: Currency and Escalation Exposure
A16: RSK-ESC | B16: Escalation Risk | C16: RSK-ESC-003 | D16: Cost Escalation Exposure | E16: PKG-05 | F16: R-008 | G16: Escalation Exposure
... A27: RSK-ESC | B27: Escalation Risk | C27: RSK-ESC-003 | D27: Cost Escalation Exposure | E27: PKG-34 | F27: R-008 | G27: Escalation Exposure — Labor Rate Increases
A28: RSK-ESC | B28: Escalation Risk | C28: RSK-ESC-003 | D28: Cost Escalation Exposure | E28: PKG-35 | F28: R-008 | G28: Escalation Exposure (MEDIUM) | H28: MEDIUM
A29: RSK-INTF | B29: Interface Risk | C29: RSK-INTF-004 | D29: Interface & Coordination Risk | E29: PKG-00 | F29: R-004 | G29: Terminal Operational Constraints and Interface Complexity
A30: RSK-INTF | B30: Interface Risk | C30: RSK-INTF-004 | D30: Interface & Coordination Risk | E30: PKG-05 | F30: R-006 | G30: Interface Coordination Complexity
A31: RSK-INTF | B31: Interface Risk | C31: RSK-INTF-004 | D31: Interface & Coordination Risk | E31: PKG-10 | F31: R-005 | G31: Interface Coordination Risk
A32: RSK-INTF | B32: Interface Risk | C32: RSK-INTF-004 | D32: Interface & Coordination Risk | E32: PKG-10 | F32: R-010 | G32: PKG-07 Rail Track Interface Risk
A33: RSK-INTF | B33: Interface Risk | C33: RSK-INTF-004 | D33: Interface & Coordination Risk | E33: PKG-11 | F33: R-005 | G33: Interface - PKG-08
A34: RSK-INTF | B34: Interface Risk | C34: RSK-INTF-004 | D34: Interface & Coordination Risk | E34: PKG-11 | F34: R-009 | G34: Interface - PKG-19
A35: RSK-INTF | B35: Interface Risk | C35: RSK-INTF-004 | D35: Interface & Coordination Risk | E35: PKG-14 | F35: R-006 | G35: Interface - PKG-10
A36: RSK-INTF | B36: Interface Risk | C36: RSK-INTF-004 | D36: Interface & Coordination Risk | E36: PKG-14 | F36: R-007 | G36: Interface - PKG-11
A37: RSK-INTF | B37: Interface Risk | C37: RSK-INTF-004 | D37: Interface & Coordination Risk | E37: PKG-14 | F37: R-008 | G37: Interface - PKG-13
A38: RSK-INTF | B38: Interface Risk | C38: RSK-INTF-004 | D38: Interface & Coordination Risk | E38: PKG-14 | F38: R-009 | G38: Interface - PKG-15
A39: RSK-INTF | B39: Interface Risk | C39: RSK-INTF-004 | D39: Interface & Coordination Risk | E39: PKG-16 | F39: R-1608 | G39: Relief Valve Set Pressure and Protected Equipment Coordina..
A40: RSK-INTF | B40: Interface Risk | C40: RSK-INTF-004 | D40: Interface & Coordination Risk | E40: PKG-22 | F40: R-007 | G40: PKG-19 Control System Interface Scope Split
... A120: RSK-PRICE | B120: Price Uncertainty | C120: RSK-PRICE-019 | D120: No Vendor Pricing/Quotes Available | E120: PKG-00 | F120: R-001 | G120: Lack of Project-Specific Pricing Sources
A121: RSK-PRICE | B121: Price Uncertainty | C121: RSK-PRICE-019 | D121: No Vendor Pricing/Quotes Available | E121: PKG-01 | F121: R-106 | G121: No Vendor Quotes — Estimate Accuracy (MEDIUM) | H121: MEDIUM
A122: RSK-PRICE | B122: Price Uncertainty | C122: RSK-PRICE-019 | D122: No Vendor Pricing/Quotes Available | E122: PKG-05 | F122: R-001 | G122: No Vendor Pricing Available
A123: RSK-PRICE | B123: Price Uncertainty | C123: RSK-PRICE-019 | D123: No Vendor Pricing/Quotes Available | E123: PKG-10 | F123: R-001 | G123: Unloading Arm Pricing Uncertainty
A124: RSK-PRICE | B124: Price Uncertainty | C124: RSK-PRICE-019 | D124: No Vendor Pricing/Quotes Available | E124: PKG-11 | F124: R-004 | G124: Price - No Quotes
A125: RSK-PRICE | B125: Price Uncertainty | C125: RSK-PRICE-019 | D125: No Vendor Pricing/Quotes Available | E125: PKG-14 | F125: R-005 | G125: Price - No Quotes
A126: RSK-PRICE | B126: Price Uncertainty | C126: RSK-PRICE-019 | D126: No Vendor Pricing/Quotes Available | E126: PKG-15 | F126: R-002 | G126: Equipment Pricing Uncertainty
A127: RSK-PRICE | B127: Price Uncertainty | C127: RSK-PRICE-019 | D127: No Vendor Pricing/Quotes Available | E127: PKG-16 | F127: R-1606 | G127: Vendor Pricing Variability
A128: RSK-PRICE | B128: Price Uncertainty | C128: RSK-PRICE-019 | D128: No Vendor Pricing/Quotes Available | E128: PKG-34 | F128: R-004 | G128: Lack of Project-Specific Pricing Sources
A129: RSK-PRICE | B129: Price Uncertainty | C129: RSK-PRICE-020 | D129: Control System Vendor Selection | E129: PKG-19 | F129: R-001 | G129: Control System Vendor Selection
A130: RSK-PRICE | B130: Price Uncertainty | C130: RSK-PRICE-021 | D130: Equipment - Loading Arm Pricing | E130: PKG-11 | F130: R-001 | G130: Equipment - Loading Arm Pricing
A131: RSK-PRICE | B131: Price Uncertainty | C131: RSK-PRICE-022 | D131: Marine Contractor Availability and Pricing Volatility | E131: PKG-08 | F131: R-806 | G131: Marine Contractor Availability and Pricing Volatility
A132: RSK-PRICE | B132: Price Uncertainty | C132: RSK-PRICE-023 | D132: Steel price volatility | E132: PKG-13 | F132: R-001 | G132: Steel price volatility
A133: RSK-PRICE | B133: Price Uncertainty | C133: RSK-PRICE-024 | D133: Vendor FAT Location | E133: PKG-19 | F133: R-008 | G133: Vendor FAT Location
... A154: RSK-QUAL | B154: Quality Risk | C154: RSK-QUAL-031 | D154: Quality/Rework Risk | E154: PKG-31 | F154: R-006 | G154: Vendor Documentation Quality/Completeness
A155: RSK-QUAL | B155: Quality Risk | C155: RSK-QUAL-031 | D155: Quality/Rework Risk | E155: PKG-35 | F155: R-004 | G155: Defects Liability Workload (MEDIUM) | H155: MEDIUM
A156: RSK-QUAL | B156: Quality Risk | C156: RSK-QUAL-032 | D156: Engineering Effort Underestimated (LOW) | E156: PKG-01 | F156: R-109 | G156: Engineering Effort Underestimated (LOW) | H156: LOW
A157: RSK-QUAL | B157: Quality Risk | C157: RSK-QUAL-033 | D157: NDE findings | E157: PKG-13 | F157: R-010 | G157: NDE findings
A158: RSK-QUAL | B158: Quality Risk | C158: RSK-QUAL-034 | D158: Underground Utility Conflicts | E158: PKG-23 | F158: R-007 | G158: Underground Utility Conflicts
A159: RSK-REG | B159: Regulatory Risk | C159: RSK-REG-035 | D159: Regulatory/Permitting Risk | E159: PKG-00 | F159: R-005 | G159: Authority Approvals and Permitting Delays
A160: RSK-REG | B160: Regulatory Risk | C160: RSK-REG-035 | D160: Regulatory/Permitting Risk | E160: PKG-08 | F160: R-804 | G160: Regulatory Approvals and Permitting Delays
A161: RSK-REG | B161: Regulatory Risk | C161: RSK-REG-035 | D161: Regulatory/Permitting Risk | E161: PKG-10 | F161: R-006 | G161: Regulatory Containment Requirements Risk
A162: RSK-REG | B162: Regulatory Risk | C162: RSK-REG-035 | D162: Regulatory/Permitting Risk | E162: PKG-11 | F162: R-013 | G162: Regulatory - Marine Terminal
A163: RSK-REG | B163: Regulatory Risk | C163: RSK-REG-035 | D163: Regulatory/Permitting Risk | E163: PKG-15 | F163: R-021 | G163: Regulatory and Code Compliance Requirements Beyond API 610
A164: RSK-REG | B164: Regulatory Risk | C164: RSK-REG-035 | D164: Regulatory/Permitting Risk | E164: PKG-21 | F164: R-007 | G164: Building Code or Permit Delays
A165: RSK-REG | B165: Regulatory Risk | C165: RSK-REG-035 | D165: Regulatory/Permitting Risk | E165: PKG-23 | F165: R-009 | G165: Code Compliance Requirements
A166: RSK-REG | B166: Regulatory Risk | C166: RSK-REG-035 | D166: Regulatory/Permitting Risk | E166: PKG-32 | F166: R-3202 | G166: Permit Condition Complexity Unknown
A167: RSK-REG | B167: Regulatory Risk | C167: RSK-REG-035 | D167: Regulatory/Permitting Risk | E167: PKG-32 | F167: R-3203 | G167: Authority Approval Timeline Risk
A168: RSK-REG | B168: Regulatory Risk | C168: RSK-REG-035 | D168: Regulatory/Permitting Risk | E168: PKG-33 | F168: R-001 | G168: HSE Regulatory Requirements Uncertainty
... A178: RSK-SCHED | B178: Schedule Risk | C178: RSK-SCHED-036 | D178: Schedule/Lead Time Risk | E178: PKG-23 | F178: R-005 | G178: Fire Protection Equipment Lead Times
A179: RSK-SCHED | B179: Schedule Risk | C179: RSK-SCHED-036 | D179: Schedule/Lead Time Risk | E179: PKG-35 | F179: R-005 | G179: Training Schedule Compression (MEDIUM) | H179: MEDIUM
A180: RSK-SCHED | B180: Schedule Risk | C180: RSK-SCHED-037 | D180: Construction Schedule Duration Variance | E180: PKG-33 | F180: R-006 | G180: Construction Schedule Duration Variance
A181: RSK-SCHED | B181: Schedule Risk | C181: RSK-SCHED-038 | D181: Employer Staffing Delays (LOW) | E181: PKG-35 | F181: R-006 | G181: Employer Staffing Delays (LOW) | H181: LOW
A182: RSK-SCHED | B182: Schedule Risk | C182: RSK-SCHED-039 | D182: Project Duration Extension | E182: PKG-34 | F182: R-002 | G182: Project Duration Extension
A183: RSK-SCOPE | B183: Scope Risk | C183: RSK-SCOPE-040 | D183: Scope Definition/Growth Risk | E183: PKG-00 | F183: R-006 | G183: Road Damage and Restoration Scope Uncertainty
A184: RSK-SCOPE | B184: Scope Risk | C184: RSK-SCOPE-040 | D184: Scope Definition/Growth Risk | E184: PKG-00 | F184: R-007 | G184: Scope Creep — Site Establishment Requirements Growth
A185: RSK-SCOPE | B185: Scope Risk | C185: RSK-SCOPE-040 | D185: Scope Definition/Growth Risk | E185: PKG-01 | F185: R-102 | G185: Dolphin 2 Marine Demolition Scope Uncertainty (HIGH) | H185: HIGH
A186: RSK-SCOPE | B186: Scope Risk | C186: RSK-SCOPE-040 | D186: Scope Definition/Growth Risk | E186: PKG-13 | F186: R-012 | G186: Phase 2 scope creep
A187: RSK-SCOPE | B187: Scope Risk | C187: RSK-SCOPE-040 | D187: Scope Definition/Growth Risk | E187: PKG-15 | F187: R-007 | G187: Engineering Scope Creep or Coordination Effort
A188: RSK-SCOPE | B188: Scope Risk | C188: RSK-SCOPE-040 | D188: Scope Definition/Growth Risk | E188: PKG-16 | F188: R-1615 | G188: Strainer and Specialty Equipment Scope Ambiguity
A189: RSK-SCOPE | B189: Scope Risk | C189: RSK-SCOPE-040 | D189: Scope Definition/Growth Risk | E189: PKG-16 | F189: R-1617 | G189: Engineering Scope Creep Risk
A190: RSK-SCOPE | B190: Scope Risk | C190: RSK-SCOPE-040 | D190: Scope Definition/Growth Risk | E190: PKG-22 | F190: R-003 | G190: Fire Suppression System Scope Uncertainty
A191: RSK-SCOPE | B191: Scope Risk | C191: RSK-SCOPE-040 | D191: Scope Definition/Growth Risk | E191: PKG-22 | F191: R-009 | G191: Interior Finishes Scope Definition
A192: RSK-SCOPE | B192: Scope Risk | C192: RSK-SCOPE-040 | D192: Scope Definition/Growth Risk | E192: PKG-32 | F192: R-3201 | G192: Permit Count and Scope Uncertainty
A193: RSK-SCOPE | B193: Scope Risk | C193: RSK-SCOPE-040 | D193: Scope Definition/Growth Risk | E193: PKG-32 | F193: R-3204 | G193: Regulatory Consultant Scope Creep
A194: RSK-SCOPE | B194: Scope Risk | C194: RSK-SCOPE-040 | D194: Scope Definition/Growth Risk | E194: PKG-33 | F194: R-002 | G194: Environmental Monitoring Scope Creep
A195: RSK-SCOPE | B195: Scope Risk | C195: RSK-SCOPE-041 | D195: Technical Design Complexity | E195: PKG-05 | F195: R-009 | G195: Seismic Requirements
A196: RSK-SCOPE | B196: Scope Risk | C196: RSK-SCOPE-041 | D196: Technical Design Complexity | E196: PKG-08 | F196: R-807 | G196: Design Changes from ER Requirements Not Yet Extracted
A197: RSK-SCOPE | B197: Scope Risk | C197: RSK-SCOPE-041 | D197: Technical Design Complexity | E197: PKG-13 | F197: R-003 | G197: Seismic complexity
... A223: RSK-SCOPE | B223: Scope Risk | C223: RSK-SCOPE-054 | D223: Food-Grade Material Requirements Risk | E223: PKG-10 | F223: R-007 | G223: Food-Grade Material Requirements Risk
A224: RSK-SCOPE | B224: Scope Risk | C224: RSK-SCOPE-055 | D224: Language/Translation Requirements (LOW) | E224: PKG-35 | F224: R-007 | G224: Language/Translation Requirements (LOW) | H224: LOW
A225: RSK-SCOPE | B225: Scope Risk | C225: RSK-SCOPE-056 | D225: Plumbing Fixture Count and Hot Water Requirements | E225: PKG-22 | F225: R-010 | G225: Plumbing Fixture Count and Hot Water Requirements
A226: RSK-SCOPE | B226: Scope Risk | C226: RSK-SCOPE-057 | D226: Scope - Arm Configuration | E226: PKG-11 | F226: R-002 | G226: Scope - Arm Configuration
A227: RSK-SCOPE | B227: Scope Risk | C227: RSK-SCOPE-058 | D227: Scope - Header Sizing | E227: PKG-14 | F227: R-002 | G227: Scope - Header Sizing
A228: RSK-SCOPE | B228: Scope Risk | C228: RSK-SCOPE-059 | D228: Scope - Phase 2 Provisions | E228: PKG-14 | F228: R-014 | G228: Scope - Phase 2 Provisions
A229: RSK-SCOPE | B229: Scope Risk | C229: RSK-SCOPE-060 | D229: Scope - Pipe Routing | E229: PKG-11 | F229: R-003 | G229: Scope - Pipe Routing
A230: RSK-SCOPE | B230: Scope Risk | C230: RSK-SCOPE-061 | D230: Scope - Piping Quantities | E230: PKG-14 | F230: R-001 | G230: Scope - Piping Quantities
A231: RSK-SCOPE | B231: Scope Risk | C231: RSK-SCOPE-062 | D231: Security Compliance Scope | E231: PKG-34 | F231: R-007 | G231: Security Compliance Scope
A232: RSK-SCOPE | B232: Scope Risk | C232: RSK-SCOPE-063 | D232: Site Reinstatement Scope (HIGH) | E232: PKG-35 | F232: R-003 | G232: Site Reinstatement Scope (HIGH) | H232: HIGH
A233: RSK-SCOPE | B233: Scope Risk | C233: RSK-SCOPE-064 | D233: Technical - Insulation Scope | E233: PKG-14 | F233: R-013 | G233: Technical - Insulation Scope
A234: RSK-SCOPE | B234: Scope Risk | C234: RSK-SCOPE-065 | D234: Training Scope Expansion (HIGH) | E234: PKG-35 | F234: R-001 | G234: Training Scope Expansion (HIGH) | H234: HIGH
A235: RSK-SCOPE | B235: Scope Risk | C235: RSK-SCOPE-066 | D235: Trenchless Crossing Monitoring Scope | E235: PKG-34 | F235: R-005 | G235: Trenchless Crossing Monitoring Scope
A236: RSK-TECH | B236: Technical Risk | C236: RSK-TECH-067 | D236: Geotechnical/Foundation Risk | E236: PKG-05 | F236: R-003 | G236: Foundation Type Uncertainty
A237: RSK-TECH | B237: Technical Risk | C237: RSK-TECH-067 | D237: Geotechnical/Foundation Risk | E237: PKG-05 | F237: R-004 | G237: Geotechnical Conditions Unknown
A238: RSK-TECH | B238: Technical Risk | C238: RSK-TECH-067 | D238: Geotechnical/Foundation Risk | E238: PKG-08 | F238: R-801 | G238: Geotechnical Conditions Worse Than Assumed
A239: RSK-TECH | B239: Technical Risk | C239: RSK-TECH-067 | D239: Geotechnical/Foundation Risk | E239: PKG-13 | F239: R-004 | G239: Foundation interface
A240: RSK-TECH | B240: Technical Risk | C240: RSK-TECH-067 | D240: Geotechnical/Foundation Risk | E240: PKG-13 | F240: R-005 | G240: Geotechnical conditions
A241: RSK-TECH | B241: Technical Risk | C241: RSK-TECH-067 | D241: Geotechnical/Foundation Risk | E241: PKG-21 | F241: R-002 | G241: Difficult Ground Conditions Requiring Piles
A242: RSK-TECH | B242: Technical Risk | C242: RSK-TECH-068 | D242: As-Built Markup Complexity | E242: PKG-31 | F242: R-005 | G242: As-Built Markup Complexity
A243: RSK-TECH | B243: Technical Risk | C243: RSK-TECH-069 | D243: Control Valve Complexity and Trim Selection Risk | E243: PKG-16 | F243: R-1604 | G243: Control Valve Complexity and Trim Selection Risk
A244: RSK-TECH | B244: Technical Risk | C244: RSK-TECH-070 | D244: Network Infrastructure Complexity | E244: PKG-19 | F244: R-010 | G244: Network Infrastructure Complexity
...

Sheet Detail
A1: LineUID | B1: FromPackageID | C1: FromDeliverableID | D1: LineID | E1: CBS | F1: WBS_PackageID | G1: WBS_DeliverableID | H1: Description | I1: Qty | J1: Unit | K1: UnitRate | L1: Amount | M1: Currency | N1: Method | O1: SourceRef | P1: Confidence | Q1: Notes | R1: Category | S1: ContingencyRate | T1: ContingencyAmount | U1: TotalWithContingency | X1: Home
A2: PKG-00::L001 | B2: PKG-00 | C2: DEL-00.01 | D2: L001 | E2: E | F2: PKG-00 | G2: DEL-00.01 | H2: Site Establishment Design Drawing Set - CAD drafting and production (4 drawings) | I2: 1 | J2: LS | K2: 12000 | L2: 12000 | M2: CAD | N2: ALLOWANCE | O2: A-001 | P2: LOW | Q2: Allowance for drawing production without vendor quotes or rate tables | R2: =VLOOKUP($F2,Inputs!$D$6:$E$41,2,FALSE) | S2: =VLOOKUP($E2,Inputs!$A$6:$B$13,2,FALSE)*Inputs!$B$2 | T2: =$L2*$S2 | U2: =$L2+$T2
A3: PKG-00::L002 | B3: PKG-00 | C3: DEL-00.02 | D3: L002 | E3: E | F3: PKG-00 | G3: DEL-00.02 | H3: Site Establishment Technical Specification - specification writing (2 specifications) | I3: 1 | J3: LS | K3: 10000 | L3: 10000 | M3: CAD | N3: ALLOWANCE | O3: A-002 | P3: LOW | Q3: Allowance for specification writing without rate tables | R3: =VLOOKUP($F3,Inputs!$D$6:$E$41,2,FALSE) | S3: =VLOOKUP($E3,Inputs!$A$6:$B$13,2,FALSE)*Inputs!$B$2 | T3: =$L3*$S3 | U3: =$L3+$T3
A4: PKG-00::L003 | B4: PKG-00 | C4: DEL-00.03 | D4: L003 | E4: PM | F4: PKG-00 | G4: DEL-00.03 | H4: Site Establishment Procedures - procedure development (3 procedures) | I4: 1 | J4: LS | K4: 9000 | L4: 9000 | M4: CAD | N4: ALLOWANCE | O4: A-003 | P4: LOW | Q4: Allowance for PM procedure development | R4: =VLOOKUP($F4,Inputs!$D$6:$E$41,2,FALSE) | S4: =VLOOKUP($E4,Inputs!$A$6:$B$13,2,FALSE)*Inputs!$B$2 | T4: =$L4*$S4 | U4: =$L4+$T4
A5: PKG-00::L004 | B5: PKG-00 | C5: DEL-00.04 | D5: L004 | E5: PM | F5: PKG-00 | G5: DEL-00.04 | H5: Contractor's Equipment Schedule - project controls documentation (2 documents) | I5: 1 | J5: LS | K5: 5000 | L5: 5000 | M5: CAD | N5: ALLOWANCE | O5: A-004 | P5: LOW | Q5: Allowance for equipment schedule preparation | R5: =VLOOKUP($F5,Inputs!$D$6:$E$41,2,FALSE) | S5: =VLOOKUP($E5,Inputs!$A$6:$B$13,2,FALSE)*Inputs!$B$2 | T5: =$L5*$S5 | U5: =$L5+$T5
A6: PKG-00::L005 | B6: PKG-00 | C6: DEL-00.05 | D6: L005 | E6: PM | F6: PKG-00 | G6: DEL-00.05 | H6: Road Access & Security Planning - access/security process documentation (3 plans) | I6: 1 | J6: LS | K6: 8000 | L6: 8000 | M6: CAD | N6: ALLOWANCE | O6: A-005 | P6: LOW | Q6: Allowance for security planning and procedure development | R6: =VLOOKUP($F6,Inputs!$D$6:$E$41,2,FALSE) | S6: =VLOOKUP($E6,Inputs!$A$6:$B$13,2,FALSE)*Inputs!$B$2 | T6: =$L6*$S6 | U6: =$L6+$T6
A7: PKG-00::L006 | B7: PKG-00 | C7: DEL-00.06 | D7: L006 | E7: E | F7: PKG-00 | G7: DEL-00.06 | H7: Pre-Works Road Condition Survey - field survey and photo documentation | I7: 1 | J7: LS | K7: 15000 | L7: 15000 | M7: CAD | N7: ALLOWANCE | O7: A-006 | P7: LOW | Q7: Allowance for surveyor services without vendor quote | R7: =VLOOKUP($F7,Inputs!$D$6:$E$41,2,FALSE) | S7: =VLOOKUP($E7,Inputs!$A$6:$B$13,2,FALSE)*Inputs!$B$2 | T7: =$L7*$S7 | U7: =$L7+$T7
A8: PKG-00::L007 | B8: PKG-00 | C8: DEL-00.07 | D8: L007 | E8: E | F8: PKG-00 | G8: DEL-00.07 | H8: Post-Works Road Condition Survey - survey and deficiency closeout | I8: 1 | J8: LS | K8: 18000 | L8: 18000 | M8: CAD | N8: ALLOWANCE | O8: A-007 | P8: LOW | Q8: Allowance for post-construction survey services | R8: =VLOOKUP($F8,Inputs!$D$6:$E$41,2,FALSE) | S8: =VLOOKUP($E8,Inputs!$A$6:$B$13,2,FALSE)*Inputs!$B$2 | T8: =$L8*$S8 | U8: =$L8+$T8
A9: PKG-00::L008 | B9: PKG-00 | C9: DEL-00.07 | D9: L008 | E9: CD | F9: PKG-00 | G9: DEL-00.07 | H9: Road Deficiency Remediation - asphalt patching and restoration work | I9: 1 | J9: LS | K9: 25000 | L9: 25000 | M9: CAD | N9: ALLOWANCE | O9: A-008 | P9: LOW | Q9: Placeholder for road restoration; highly variable based on actual damage | R9: =VLOOKUP($F9,Inputs!$D$6:$E$41,2,FALSE) | S9: =VLOOKUP($E9,Inputs!$A$6:$B$13,2,FALSE)*Inputs!$B$2 | T9: =$L9*$S9 | U9: =$L9+$T9
A10: PKG-00::L009 | B10: PKG-00 | C10: DEL-00.08 | D10: L009 | E10: E | F10: PKG-00 | G10: DEL-00.08 | H10: Temporary Water Supply Design - utility design drawings (3 drawings) | I10: 1 | J10: LS | K10: 10000 | L10: 10000 | M10: CAD | N10: ALLOWANCE | O10: A-009 | P10: LOW | Q10: Allowance for water supply design effort | R10: =VLOOKUP($F10,Inputs!$D$6:$E$41,2,FALSE) | S10: =VLOOKUP($E10,Inputs!$A$6:$B$13,2,FALSE)*Inputs!$B$2 | T10: =$L10*$S10 | U10: =$L10+$T10
A11: PKG-00::L010 | B11: PKG-00 | C11: DEL-00.08 | D11: L010 | E11: MAT | F11: PKG-00 | G11: DEL-00.08 | H11: Temporary Water Supply Materials - pipe fittings backflow preventer valves | I11: 1 | J11: LS | K11: 20000 | L11: 20000 | M11: CAD | N11: ALLOWANCE | O11: A-010 | P11: LOW | Q11: Material allowance without vendor quotes or site layout distances | R11: =VLOOKUP($F11,Inputs!$D$6:$E$41,2,FALSE) | S11: =VLOOKUP($E11,Inputs!$A$6:$B$13,2,FALSE)*Inputs!$B$2 | T11: =$L11*$S11 | U11: =$L11+$T11
A12: PKG-00::L011 | B12: PKG-00 | C12: DEL-00.08 | D12: L011 | E12: CD | F12: PKG-00 | G12: DEL-00.08 | H12: Temporary Water Supply Installation - plumbing labor connection testing | I12: 1 | J12: LS | K12: 25000 | L12: 25000 | M12: CAD | N12: ALLOWANCE | O12: A-010 | P12: LOW | Q12: Installation labor allowance without rate tables | R12: =VLOOKUP($F12,Inputs!$D$6:$E$41,2,FALSE) | S12: =VLOOKUP($E12,Inputs!$A$6:$B$13,2,FALSE)*Inputs!$B$2 | T12: =$L12*$S12 | U12: =$L12+$T12
A13: PKG-00::L012 | B13: PKG-00 | C13: DEL-00.05 | D13: L012 | E13: CD | F13: PKG-00 | G13: DEL-00.05 | H13: Security Gate & Access Control Installation - gate hardware and system install | I13: 1 | J13: LS | K13: 75000 | L13: 75000 | M13: CAD | N13: ALLOWANCE | O13: A-011 | P13: LOW | Q13: Allowance for security equipment and installation | R13: =VLOOKUP($F13,Inputs!$D$6:$E$41,2,FALSE) | S13: =VLOOKUP($E13,Inputs!$A$6:$B$13,2,FALSE)*Inputs!$B$2 | T13: =$L13*$S13 | U13: =$L13+$T13
A14: PKG-00::L013 | B14: PKG-00 | D14: L013 | E14: MAT | F14: PKG-00 | H14: Temporary Site Facilities - Materials (office trailers welfare facilities fencing) | I14: 1 | J14: LS | K14: 500000 | L14: 500000 | M14: CAD | N14: ALLOWANCE | O14: A-012 | P14: LOW | Q14: Material component of site facilities allowance; breakdown: trailers $300k fencing $150k misc $50k | R14: =VLOOKUP($F14,Inputs!$D$6:$E$41,2,FALSE) | S14: =VLOOKUP($E14,Inputs!$A$6:$B$13,2,FALSE)*Inputs!$B$2 | T14: =$L14*$S14 | U14: =$L14+$T14
A15: PKG-00::L014 | B15: PKG-00 | D15: L014 | E15: CD | F15: PKG-00 | H15: Temporary Site Infrastructure - Construction (laydown electrical utilities signage) | I15: 1 | J15: LS | K15: 350000 | L15: 350000 | M15: CAD | N15: ALLOWANCE | O15: A-012 | P15: LOW | Q15: Construction component of site infrastructure allowance; breakdown: laydown $150k electrical $120k welfare $80k | R15: =VLOOKUP($F15,Inputs!$D$6:$E$41,2,FALSE) | S15: =VLOOKUP($E15,Inputs!$A$6:$B$13,2,FALSE)*Inputs!$B$2 | T15: =$L15*$S15 | U15: =$L15+$T15
A16: PKG-00::L015 | B16: PKG-00 | D16: L015 | E16: CI | F16: PKG-00 | H16: Security Gate Staffing - construction phase security operations | I16: 1 | J16: LS | K16: 180000 | L16: 180000 | M16: CAD | N16: ALLOWANCE | O16: A-013 | P16: LOW | Q16: 24-month gate staffing allowance (12hr/day 6day/week @ $30/hr); hours TBD from schedule | R16: =VLOOKUP($F16,Inputs!$D$6:$E$41,2,FALSE) | S16: =VLOOKUP($E16,Inputs!$A$6:$B$13,2,FALSE)*Inputs!$B$2 | T16: =$L16*$S16 | U16: =$L16+$T16
A17: PKG-00::L016 | B17: PKG-00 | D17: L016 | E17: CI | F17: PKG-00 | H17: Construction Indirects - field supervision site overhead QA/QC (factor-based) | I17: 1 | J17: LS | K17: 85500 | L17: 85500 | M17: CAD | N17: PARAMETRIC | O17: D-006 | P17: LOW | Q17: 18% of CD base ($475k CD × 0.18); factor from fallback model | R17: =VLOOKUP($F17,Inputs!$D$6:$E$41,2,FALSE) | S17: =VLOOKUP($E17,Inputs!$A$6:$B$13,2,FALSE)*Inputs!$B$2 | T17: =$L17*$S17 | U17: =$L17+$T17
A18: PKG-00::L017 | B18: PKG-00 | D18: L017 | E18: PM | F18: PKG-00 | H18: EPCM / Project Management - PKG-00 allocation (factor-based) | I18: 1 | J18: LS | K18: 75630 | L18: 75630 | M18: CAD | N18: PARAMETRIC | O18: D-006 | P18: MED | Q18: 6% of (CD+CI+MAT) = 6% × ($475k + $265.5k + $520k) = $75.6k; factor from fallback model | R18: =VLOOKUP($F18,Inputs!$D$6:$E$41,2,FALSE) | S18: =VLOOKUP($E18,Inputs!$A$6:$B$13,2,FALSE)*Inputs!$B$2 | T18: =$L18*$S18 | U18: =$L18+$T18
A19: PKG-00::L018 | B19: PKG-00 | D19: L018 | E19: P | F19: PKG-00 | H19: Procurement Services - vendor coordination expediting (factor-based) | I19: 1 | J19: LS | K19: 10400 | L19: 10400 | M19: CAD | N19: PARAMETRIC | O19: D-006 | P19: MED | Q19: 2% of MAT = 2% × $520k; factor from fallback model | R19: =VLOOKUP($F19,Inputs!$D$6:$E$41,2,FALSE) | S19: =VLOOKUP($E19,Inputs!$A$6:$B$13,2,FALSE)*Inputs!$B$2 | T19: =$L19*$S19 | U19: =$L19+$T19
A20: PKG-01::L101 | B20: PKG-01 | C20: DEL-01.01 | D20: L101 | E20: E | F20: PKG-01 | G20: DEL-01.01 | H20: Demolition Design Drawing Set - CAD drafting and production (demolition plans removal sequence disposal location plans ~6 drawings) | I20: 1 | J20: LS | K20: 18000 | L20: 18000 | M20: CAD | N20: ALLOWANCE | O20: A-101 | P20: LOW | Q20: Allowance for demolition drawing production; more complex than site establishment due to phasing and marine interface | R20: =VLOOKUP($F20,Inputs!$D$6:$E$41,2,FALSE) | S20: =VLOOKUP($E20,Inputs!$A$6:$B$13,2,FALSE)*Inputs!$B$2 | T20: =$L20*$S20 | U20: =$L20+$T20
A21: PKG-01::L102 | B21: PKG-01 | C21: DEL-01.02 | D21: L102 | E21: E | F21: PKG-01 | G21: DEL-01.02 | H21: Demolition Technical Specification - specification writing (demolition spec disposal requirements) | I21: 1 | J21: LS | K21: 15000 | L21: 15000 | M21: CAD | N21: ALLOWANCE | O21: A-102 | P21: LOW | Q21: Allowance for specification writing; includes performance materials workmanship and disposal requirements sections | R21: =VLOOKUP($F21,Inputs!$D$6:$E$41,2,FALSE) | S21: =VLOOKUP($E21,Inputs!$A$6:$B$13,2,FALSE)*Inputs!$B$2 | T21: =$L21*$S21 | U21: =$L21+$T21
A22: PKG-01::L103 | B22: PKG-01 | C22: DEL-01.03 | D22: L103 | E22: PM | F22: PKG-01 | G22: DEL-01.03 | H22: Demolition Procedures - method statement and procedure development (5 procedures: general plus Track 6 Dolphin 2 fencing salt tent) | I22: 1 | J22: LS | K22: 25000 | L22: 25000 | M22: CAD | N22: ALLOWANCE | O22: A-103 | P22: LOW | Q22: Allowance for HSE procedure development; Track 6 and Dolphin 2 procedures require specialized content | R22: =VLOOKUP($F22,Inputs!$D$6:$E$41,2,FALSE) | S22: =VLOOKUP($E22,Inputs!$A$6:$B$13,2,FALSE)*Inputs!$B$2 | T22: =$L22*$S22 | U22: =$L22+$T22
A23: PKG-01::L104 | B23: PKG-01 | C23: DEL-01.04 | D23: L104 | E23: E | F23: PKG-01 | G23: DEL-01.04 | H23: Demolition Installation & Test Records - QA/QC documentation setup and record preparation | I23: 1 | J23: LS | K23: 8000 | L23: 8000 | M23: CAD | N23: ALLOWANCE | O23: A-104 | P23: LOW | Q23: Allowance for QA/QC documentation templates record setup and closeout documentation | R23: =VLOOKUP($F23,Inputs!$D$6:$E$41,2,FALSE) | S23: =VLOOKUP($E23,Inputs!$A$6:$B$13,2,FALSE)*Inputs!$B$2 | T23: =$L23*$S23 | U23: =$L23+$T23
A24: PKG-01::L105 | B24: PKG-01 | D24: L105 | E24: CD | F24: PKG-01 | H24: Track 6 Rail Demolition - rail track removal ballast removal tie disposal (assume ~500 LF rail track) | I24: 1 | J24: LS | K24: 175000 | L24: 175000 | M24: CAD | N24: ALLOWANCE | O24: A-105 | P24: LOW | Q24: Placeholder for Track 6 demolition; actual cost depends on track length condition and ballast contamination status | R24: =VLOOKUP($F24,Inputs!$D$6:$E$41,2,FALSE) | S24: =VLOOKUP($E24,Inputs!$A$6:$B$13,2,FALSE)*Inputs!$B$2 | T24: =$L24*$S24 | U24: =$L24+$T24
A25: PKG-01::L106 | B25: PKG-01 | D25: L106 | E25: CD | F25: PKG-01 | H25: Dolphin 2 Marine Demolition - marine structure removal including barge/crane mobilization pile cutting deck removal marine debris control | I25: 1 | J25: LS | K25: 450000 | L25: 450000 | M25: CAD | N25: ALLOWANCE | O25: A-106 | P25: LOW | Q25: Marine demolition requires specialized marine equipment and crew; placeholder based on typical marine pile structure removal - highly variable | R25: =VLOOKUP($F25,Inputs!$D$6:$E$41,2,FALSE) | S25: =VLOOKUP($E25,Inputs!$A$6:$B$13,2,FALSE)*Inputs!$B$2 | T25: =$L25*$S25 | U25: =$L25+$T25
A26: PKG-01::L107 | B26: PKG-01 | D26: L107 | E26: CD | F26: PKG-01 | H26: Fencing Removal - perimeter fencing demolition and disposal (assume ~2000 LF chain-link or similar) | I26: 1 | J26: LS | K26: 35000 | L26: 35000 | M26: CAD | N26: ALLOWANCE | O26: A-107 | P26: LOW | Q26: Placeholder for fencing removal; relatively simple scope but length unknown | R26: =VLOOKUP($F26,Inputs!$D$6:$E$41,2,FALSE) | S26: =VLOOKUP($E26,Inputs!$A$6:$B$13,2,FALSE)*Inputs!$B$2 | T26: =$L26*$S26 | U26: =$L26+$T26
A27: PKG-01::L108 | B27: PKG-01 | D27: L108 | E27: CD | F27: PKG-01 | H27: Salt Tent Dismantling - building structure demolition foundation removal site restoration | I27: 1 | J27: LS | K27: 125000 | L27: 125000 | M27: CAD | N27: ALLOWANCE | O27: A-108 | P27: LOW | Q27: Placeholder for salt tent demolition; cost depends on structure type size and foundation requirements | R27: =VLOOKUP($F27,Inputs!$D$6:$E$41,2,FALSE) | S27: =VLOOKUP($E27,Inputs!$A$6:$B$13,2,FALSE)*Inputs!$B$2 | T27: =$L27*$S27 | U27: =$L27+$T27
A28: PKG-01::L109 | B28: PKG-01 | D28: L109 | E28: MAT | F28: PKG-01 | H28: Demolition Materials and Temporary Works - protection barriers dust control erosion control disposal containers | I28: 1 | J28: LS | K28: 40000 | L28: 40000 | M28: CAD | N28: ALLOWANCE | O28: A-109 | P28: LOW | Q28: Materials allowance for temporary works and protection measures during demolition | R28: =VLOOKUP($F28,Inputs!$D$6:$E$41,2,FALSE) | S28: =VLOOKUP($E28,Inputs!$A$6:$B$13,2,FALSE)*Inputs!$B$2 | T28: =$L28*$S28 | U28: =$L28+$T28
A29: PKG-01::L110 | B29: PKG-01 | D29: L110 | E29: CD | F29: PKG-01 | H29: Hazardous Materials Contingency Placeholder - potential asbestos lead or contaminated materials (hazmat survey pending) | I29: 1 | J29: LS | K29: 75000 | L29: 75000 | M29: CAD | N29: ALLOWANCE | O29: A-110 | P29: LOW | Q29: Contingency placeholder per D-016; hazmat presence unknown - if survey confirms hazmat actual costs may be significantly higher | R29: =VLOOKUP($F29,Inputs!$D$6:$E$41,2,FALSE) | S29: =VLOOKUP($E29,Inputs!$A$6:$B$13,2,FALSE)*Inputs!$B$2 | T29: =$L29*$S29 | U29: =$L29+$T29
A30: PKG-01::L111 | B30: PKG-01 | D30: L111 | E30: CD | F30: PKG-01 | H30: Waste Disposal and Hauling - demolition waste transport to disposal/recycling facilities (concrete steel wood rail materials) | I30: 1 | J30: LS | K30: 95000 | L30: 95000 | M30: CAD | N30: ALLOWANCE | O30: A-111 | P30: LOW | Q30: Placeholder for waste disposal; actual cost depends on material volumes disposal distances and tipping fees | R30: =VLOOKUP($F30,Inputs!$D$6:$E$41,2,FALSE) | S30: =VLOOKUP($E30,Inputs!$A$6:$B$13,2,FALSE)*Inputs!$B$2 | T30: =$L30*$S30 | U30: =$L30+$T30
A31: PKG-01::L112 | B31: PKG-01 | D31: L112 | E31: CI | F31: PKG-01 | H31: Construction Indirects - field supervision safety oversight QA/QC coordination (factor-based) | I31: 1 | J31: LS | K31: 171000 | L31: 171000 | M31: CAD | N31: PARAMETRIC | O31: D-017 | P31: LOW | Q31: 18% of CD base ($950k CD x 0.18 = $171k); factor from fallback model per D-017 | R31: =VLOOKUP($F31,Inputs!$D$6:$E$41,2,FALSE) | S31: =VLOOKUP($E31,Inputs!$A$6:$B$13,2,FALSE)*Inputs!$B$2 | T31: =$L31*$S31 | U31: =$L31+$T31
A32: PKG-01::L113 | B32: PKG-01 | D32: L113 | E32: PM | F32: PKG-01 | H32: EPCM / Project Management - PKG-01 allocation (factor-based) | I32: 1 | J32: LS | K32: 69660 | L32: 69660 | M32: CAD | N32: PARAMETRIC | O32: D-017 | P32: MED | Q32: 6% of (CD+CI+MAT) = 6% x ($950k + $171k + $40k) = $69.7k; factor from fallback model per D-017 | R32: =VLOOKUP($F32,Inputs!$D$6:$E$41,2,FALSE) | S32: =VLOOKUP($E32,Inputs!$A$6:$B$13,2,FALSE)*Inputs!$B$2 | T32: =$L32*$S32 | U32: =$L32+$T32
A33: PKG-01::L114 | B33: PKG-01 | D33: L114 | E33: P | F33: PKG-01 | H33: Procurement Services - vendor coordination expediting (factor-based) | I33: 1 | J33: LS | K33: 800 | L33: 800 | M33: CAD | N33: PARAMETRIC | O33: D-017 | P33: MED | Q33: 2% of MAT = 2% x $40k = $800; factor from fallback model per D-017 | R33: =VLOOKUP($F33,Inputs!$D$6:$E$41,2,FALSE) | S33: =VLOOKUP($E33,Inputs!$A$6:$B$13,2,FALSE)*Inputs!$B$2 | T33: =$L33*$S33 | U33: =$L33+$T33
A34: PKG-02::L001 | B34: PKG-02 | C34: DEL-02.01 | D34: L001 | E34: E | F34: PKG-02 | G34: DEL-02.01 | H34: Earthworks Design Drawing Set - CAD drafting (grading plans cut/fill plans ground improvement sections) | I34: 1 | J34: LS | K34: 25000 | L34: 25000 | M34: CAD | N34: ALLOWANCE | O34: A-001 | P34: LOW | Q34: ~8-10 sheets at $3k/sheet average | R34: =VLOOKUP($F34,Inputs!$D$6:$E$41,2,FALSE) | S34: =VLOOKUP($E34,Inputs!$A$6:$B$13,2,FALSE)*Inputs!$B$2 | T34: =$L34*$S34 | U34: =$L34+$T34
A35: PKG-02::L002 | B35: PKG-02 | C35: DEL-02.02 | D35: L002 | E35: E | F35: PKG-02 | G35: DEL-02.02 | H35: Earthworks Technical Specification - specification writing (earthworks ground improvement geotextile specs) | I35: 1 | J35: LS | K35: 8000 | L35: 8000 | M35: CAD | N35: ALLOWANCE | O35: A-002 | P35: LOW | Q35: ~50 hours at $150/hr | R35: =VLOOKUP($F35,Inputs!$D$6:$E$41,2,FALSE) | S35: =VLOOKUP($E35,Inputs!$A$6:$B$13,2,FALSE)*Inputs!$B$2 | T35: =$L35*$S35 | U35: =$L35+$T35
A36: PKG-02::L003 | B36: PKG-02 | C36: DEL-02.03 | D36: L003 | E36: E | F36: PKG-02 | G36: DEL-02.03 | H36: Earthworks Design Calculations - cut/fill calculations bearing capacity settlement analysis | I36: 1 | J36: LS | K36: 12000 | L36: 12000 | M36: CAD | N36: ALLOWANCE | O36: A-003 | P36: LOW | Q36: ~70 hours at $175/hr | R36: =VLOOKUP($F36,Inputs!$D$6:$E$41,2,FALSE) | S36: =VLOOKUP($E36,Inputs!$A$6:$B$13,2,FALSE)*Inputs!$B$2 | T36: =$L36*$S36 | U36: =$L36+$T36
A37: PKG-02::L004 | B37: PKG-02 | C37: DEL-02.04 | D37: L004 | E37: E | F37: PKG-02 | G37: DEL-02.04 | H37: Geotechnical Investigation - field drilling program (15-20 boreholes 15-25m deep) | I37: 1 | J37: LS | K37: 100000 | L37: 100000 | M37: CAD | N37: ALLOWANCE | O37: A-004 | P37: LOW | Q37: Drilling mobilization boreholes sampling monitoring wells | R37: =VLOOKUP($F37,Inputs!$D$6:$E$41,2,FALSE) | S37: =VLOOKUP($E37,Inputs!$A$6:$B$13,2,FALSE)*Inputs!$B$2 | T37: =$L37*$S37 | U37: =$L37+$T37
A38: PKG-02::L005 | B38: PKG-02 | C38: DEL-02.04 | D38: L005 | E38: E | F38: PKG-02 | G38: DEL-02.04 | H38: Geotechnical Laboratory Testing - soil classification strength compaction tests | I38: 1 | J38: LS | K38: 25000 | L38: 25000 | M38: CAD | N38: ALLOWANCE | O38: A-005 | P38: LOW | Q38: Full lab program for design parameters | R38: =VLOOKUP($F38,Inputs!$D$6:$E$41,2,FALSE) | S38: =VLOOKUP($E38,Inputs!$A$6:$B$13,2,FALSE)*Inputs!$B$2 | T38: =$L38*$S38 | U38: =$L38+$T38
A39: PKG-02::L006 | B39: PKG-02 | C39: DEL-02.04 | D39: L006 | E39: E | F39: PKG-02 | G39: DEL-02.04 | H39: Geotechnical Reporting - investigation report and ground improvement design | I39: 1 | J39: LS | K39: 18000 | L39: 18000 | M39: CAD | N39: ALLOWANCE | O39: A-006 | P39: LOW | Q39: ~100 hours engineering time | R39: =VLOOKUP($F39,Inputs!$D$6:$E$41,2,FALSE) | S39: =VLOOKUP($E39,Inputs!$A$6:$B$13,2,FALSE)*Inputs!$B$2 | T39: =$L39*$S39 | U39: =$L39+$T39
A40: PKG-02::L007 | B40: PKG-02 | C40: DEL-02.05 | D40: L007 | E40: E | F40: PKG-02 | G40: DEL-02.05 | H40: Topographic Survey - site survey including utility locates (~7 ha) | I40: 1 | J40: LS | K40: 55000 | L40: 55000 | M40: CAD | N40: ALLOWANCE | O40: A-007 | P40: LOW | Q40: Survey and CAD deliverables | R40: =VLOOKUP($F40,Inputs!$D$6:$E$41,2,FALSE) | S40: =VLOOKUP($E40,Inputs!$A$6:$B$13,2,FALSE)*Inputs!$B$2 | T40: =$L40*$S40 | U40: =$L40+$T40
A41: PKG-02::L008 | B41: PKG-02 | C41: DEL-02.06 | D41: L008 | E41: E | F41: PKG-02 | G41: DEL-02.06 | H41: Earthworks QA/QC Records Compilation - test records documentation | I41: 1 | J41: LS | K41: 12000 | L41: 12000 | M41: CAD | N41: ALLOWANCE | O41: A-009 | P41: LOW | Q41: ~120 hours record compilation | R41: =VLOOKUP($F41,Inputs!$D$6:$E$41,2,FALSE) | S41: =VLOOKUP($E41,Inputs!$A$6:$B$13,2,FALSE)*Inputs!$B$2 | T41: =$L41*$S41 | U41: =$L41+$T41
A42: PKG-02::L009 | B42: PKG-02 | C42: DEL-02.07 | D42: L009 | E42: E | F42: PKG-02 | G42: DEL-02.07 | H42: Excavation & Fill Placement Method Statement - procedure development | I42: 1 | J42: LS | K42: 6000 | L42: 6000 | M42: CAD | N42: ALLOWANCE | O42: A-010 | P42: LOW | Q42: ~40 hours at $140/hr | R42: =VLOOKUP($F42,Inputs!$D$6:$E$41,2,FALSE) | S42: =VLOOKUP($E42,Inputs!$A$6:$B$13,2,FALSE)*Inputs!$B$2 | T42: =$L42*$S42 | U42: =$L42+$T42
A43: PKG-02::L010 | B43: PKG-02 | C43: DEL-02.08 | D43: L010 | E43: E | F43: PKG-02 | G43: DEL-02.08 | H43: Sampling & Testing Program Development | I43: 1 | J43: LS | K43: 4000 | L43: 4000 | M43: CAD | N43: ALLOWANCE | O43: A-011 | P43: LOW | Q43: ~30 hours | R43: =VLOOKUP($F43,Inputs!$D$6:$E$41,2,FALSE) | S43: =VLOOKUP($E43,Inputs!$A$6:$B$13,2,FALSE)*Inputs!$B$2 | T43: =$L43*$S43 | U43: =$L43+$T43
A44: PKG-02::L011 | B44: PKG-02 | C44: DEL-02.09 | D44: L011 | E44: E | F44: PKG-02 | G44: DEL-02.09 | H44: Compaction Verification Plan Development | I44: 1 | J44: LS | K44: 3500 | L44: 3500 | M44: CAD | N44: ALLOWANCE | O44: A-012 | P44: LOW | Q44: ~25 hours | R44: =VLOOKUP($F44,Inputs!$D$6:$E$41,2,FALSE) | S44: =VLOOKUP($E44,Inputs!$A$6:$B$13,2,FALSE)*Inputs!$B$2 | T44: =$L44*$S44 | U44: =$L44+$T44
A45: PKG-02::L012 | B45: PKG-02 | D45: L012 | E45: CD | F45: PKG-02 | H45: Site Stripping & Grubbing - topsoil removal vegetation clearing (~5 ha) | I45: 1 | J45: LS | K45: 75000 | L45: 75000 | M45: CAD | N45: ALLOWANCE | O45: A-013 | P45: LOW | Q45: $15k/ha × 5 ha | R45: =VLOOKUP($F45,Inputs!$D$6:$E$41,2,FALSE) | S45: =VLOOKUP($E45,Inputs!$A$6:$B$13,2,FALSE)*Inputs!$B$2 | T45: =$L45*$S45 | U45: =$L45+$T45
A46: PKG-02::L013 | B46: PKG-02 | D46: L013 | E46: CD | F46: PKG-02 | H46: Excavation - cut to design grades (~15000 m³) | I46: 1 | J46: LS | K46: 180000 | L46: 180000 | M46: CAD | N46: ALLOWANCE | O46: A-014 | P46: LOW | Q46: $12/m³ × 15000 m³ | R46: =VLOOKUP($F46,Inputs!$D$6:$E$41,2,FALSE) | S46: =VLOOKUP($E46,Inputs!$A$6:$B$13,2,FALSE)*Inputs!$B$2 | T46: =$L46*$S46 | U46: =$L46+$T46
A47: PKG-02::L014 | B47: PKG-02 | D47: L014 | E47: MAT | F47: PKG-02 | H47: Imported Structural Fill Material - supply of engineered fill (~25000 m³) | I47: 1 | J47: LS | K47: 375000 | L47: 375000 | M47: CAD | N47: ALLOWANCE | O47: A-015 | P47: LOW | Q47: $15/m³ × 25000 m³ material only | R47: =VLOOKUP($F47,Inputs!$D$6:$E$41,2,FALSE) | S47: =VLOOKUP($E47,Inputs!$A$6:$B$13,2,FALSE)*Inputs!$B$2 | T47: =$L47*$S47 | U47: =$L47+$T47
A48: PKG-02::L015 | B48: PKG-02 | D48: L015 | E48: CD | F48: PKG-02 | H48: Fill Placement & Compaction - place and compact in lifts (~25000 m³) | I48: 1 | J48: LS | K48: 250000 | L48: 250000 | M48: CAD | N48: ALLOWANCE | O48: A-015 | P48: LOW | Q48: $10/m³ placement and compaction labor | R48: =VLOOKUP($F48,Inputs!$D$6:$E$41,2,FALSE) | S48: =VLOOKUP($E48,Inputs!$A$6:$B$13,2,FALSE)*Inputs!$B$2 | T48: =$L48*$S48 | U48: =$L48+$T48
A49: PKG-02::L016 | B49: PKG-02 | D49: L016 | E49: MAT | F49: PKG-02 | H49: Ground Improvement Materials - stone columns/aggregate (~30000 m²) | I49: 1 | J49: LS | K49: 600000 | L49: 600000 | M49: CAD | N49: ALLOWANCE | O49: A-016 | P49: LOW | Q49: $20/m² material component | R49: =VLOOKUP($F49,Inputs!$D$6:$E$41,2,FALSE) | S49: =VLOOKUP($E49,Inputs!$A$6:$B$13,2,FALSE)*Inputs!$B$2 | T49: =$L49*$S49 | U49: =$L49+$T49
A50: PKG-02::L017 | B50: PKG-02 | D50: L017 | E50: CD | F50: PKG-02 | H50: Ground Improvement Installation - vibro-compaction/stone columns (~30000 m²) | I50: 1 | J50: LS | K50: 900000 | L50: 900000 | M50: CAD | N50: ALLOWANCE | O50: A-017 | P50: LOW | Q50: $30/m² installation | R50: =VLOOKUP($F50,Inputs!$D$6:$E$41,2,FALSE) | S50: =VLOOKUP($E50,Inputs!$A$6:$B$13,2,FALSE)*Inputs!$B$2 | T50: =$L50*$S50 | U50: =$L50+$T50
A51: PKG-02::L018 | B51: PKG-02 | D51: L018 | E51: CD | F51: PKG-02 | H51: Compaction Testing - nuclear density/sand cone tests (~50 tests) | I51: 1 | J51: LS | K51: 25000 | L51: 25000 | M51: CAD | N51: ALLOWANCE | O51: A-018 | P51: LOW | Q51: Testing during fill placement | R51: =VLOOKUP($F51,Inputs!$D$6:$E$41,2,FALSE) | S51: =VLOOKUP($E51,Inputs!$A$6:$B$13,2,FALSE)*Inputs!$B$2 | T51: =$L51*$S51 | U51: =$L51+$T51
A52: PKG-02::L019 | B52: PKG-02 | D52: L019 | E52: CD | F52: PKG-02 | H52: Proof Rolling - verification of structural areas | I52: 1 | J52: LS | K52: 15000 | L52: 15000 | M52: CAD | N52: ALLOWANCE | O52: A-019 | P52: LOW | Q52: Proof roll with loaded truck | R52: =VLOOKUP($F52,Inputs!$D$6:$E$41,2,FALSE) | S52: =VLOOKUP($E52,Inputs!$A$6:$B$13,2,FALSE)*Inputs!$B$2 | T52: =$L52*$S52 | U52: =$L52+$T52
A53: PKG-02::L020 | B53: PKG-02 | D53: L020 | E53: CD | F53: PKG-02 | H53: Dewatering - temporary dewatering for excavations | I53: 1 | J53: LS | K53: 50000 | L53: 50000 | M53: CAD | N53: ALLOWANCE | O53: A-021 | P53: LOW | Q53: Pumping and disposal allowance | R53: =VLOOKUP($F53,Inputs!$D$6:$E$41,2,FALSE) | S53: =VLOOKUP($E53,Inputs!$A$6:$B$13,2,FALSE)*Inputs!$B$2 | T53: =$L53*$S53 | U53: =$L53+$T53
A54: PKG-02::L021 | B54: PKG-02 | D54: L021 | E54: MAT | F54: PKG-02 | H54: Geotextile Separation Layer - fabric under fill areas (~20000 m²) | I54: 1 | J54: LS | K54: 160000 | L54: 160000 | M54: CAD | N54: ALLOWANCE | O54: A-022 | P54: LOW | Q54: $8/m² installed | R54: =VLOOKUP($F54,Inputs!$D$6:$E$41,2,FALSE) | S54: =VLOOKUP($E54,Inputs!$A$6:$B$13,2,FALSE)*Inputs!$B$2 | T54: =$L54*$S54 | U54: =$L54+$T54
A55: PKG-02::L022 | B55: PKG-02 | D55: L022 | E55: CD | F55: PKG-02 | H55: Fine Grading - final grade preparation for pavements/structures | I55: 1 | J55: LS | K55: 45000 | L55: 45000 | M55: CAD | N55: ALLOWANCE | O55: D-012 | P55: LOW | Q55: ~5 ha at $9k/ha | R55: =VLOOKUP($F55,Inputs!$D$6:$E$41,2,FALSE) | S55: =VLOOKUP($E55,Inputs!$A$6:$B$13,2,FALSE)*Inputs!$B$2 | T55: =$L55*$S55 | U55: =$L55+$T55
A56: PKG-02::L023 | B56: PKG-02 | D56: L023 | E56: CD | F56: PKG-02 | H56: Erosion & Sediment Control - temporary measures during construction | I56: 1 | J56: LS | K56: 35000 | L56: 35000 | M56: CAD | N56: ALLOWANCE | O56: D-012 | P56: LOW | Q56: Silt fence sediment traps | R56: =VLOOKUP($F56,Inputs!$D$6:$E$41,2,FALSE) | S56: =VLOOKUP($E56,Inputs!$A$6:$B$13,2,FALSE)*Inputs!$B$2 | T56: =$L56*$S56 | U56: =$L56+$T56
... A60: PKG-02::L027 | B60: PKG-02 | D60: L027 | E60: COM | F60: PKG-02 | H60: Testing & Verification - final verification testing reporting | I60: 1 | J60: LS | K60: 88000 | L60: 88000 | M60: CAD | N60: PARAMETRIC | O60: D-009 | P60: LOW | Q60: 3% of (CD+CI+MAT) base | R60: =VLOOKUP($F60,Inputs!$D$6:$E$41,2,FALSE) | S60: =VLOOKUP($E60,Inputs!$A$6:$B$13,2,FALSE)*Inputs!$B$2 | T60: =$L60*$S60 | U60: =$L60+$T60
A61: PKG-03::L-001 | B61: PKG-03 | C61: DEL-03.01 | D61: L-001 | E61: E | F61: PKG-03 | G61: DEL-03.01 | H61: Civil engineering design - Underground Utilities Design Drawing Set | I61: 1 | J61: LS | K61: 65000 | L61: 65000 | M61: CAD | N61: ALLOWANCE | O61: A-006 | P61: LOW | Q61: Drawing set production including storm drainage plans/profiles; OWS layout; duct banks; trenchless crossings; CAD technician hours included | R61: =VLOOKUP($F61,Inputs!$D$6:$E$41,2,FALSE) | S61: =VLOOKUP($E61,Inputs!$A$6:$B$13,2,FALSE)*Inputs!$B$2 | T61: =$L61*$S61 | U61: =$L61+$T61
A62: PKG-03::L-002 | B62: PKG-03 | C62: DEL-03.02 | D62: L-002 | E62: E | F62: PKG-03 | G62: DEL-03.02 | H62: Civil engineering design - Underground Utilities Technical Specification | I62: 1 | J62: LS | K62: 45000 | L62: 45000 | M62: CAD | N62: ALLOWANCE | O62: A-006 | P62: LOW | Q62: Specification development for storm drainage; OWS; duct banks; trenchless crossings; materials and workmanship requirements | R62: =VLOOKUP($F62,Inputs!$D$6:$E$41,2,FALSE) | S62: =VLOOKUP($E62,Inputs!$A$6:$B$13,2,FALSE)*Inputs!$B$2 | T62: =$L62*$S62 | U62: =$L62+$T62
A63: PKG-03::L-003 | B63: PKG-03 | C63: DEL-03.03 | D63: L-003 | E63: E | F63: PKG-03 | G63: DEL-03.03 | H63: Civil engineering design - Underground Utilities Design Calculations | I63: 1 | J63: LS | K63: 55000 | L63: 55000 | M63: CAD | N63: ALLOWANCE | O63: A-006 | P63: LOW | Q63: Hydraulic calculations; OWS sizing; duct bank capacity analysis; trenchless crossing structural calculations | R63: =VLOOKUP($F63,Inputs!$D$6:$E$41,2,FALSE) | S63: =VLOOKUP($E63,Inputs!$A$6:$B$13,2,FALSE)*Inputs!$B$2 | T63: =$L63*$S63 | U63: =$L63+$T63
A64: PKG-03::L-004 | B64: PKG-03 | C64: DEL-03.04 | D64: L-004 | E64: E | F64: PKG-03 | G64: DEL-03.04 | H64: Civil engineering design - Underground Utilities Data Sheet Package | I64: 1 | J64: LS | K64: 35000 | L64: 35000 | M64: CAD | N64: ALLOWANCE | O64: A-006 | P64: LOW | Q64: Equipment and material data sheets for OWS; pipes; instrumentation; pumps | R64: =VLOOKUP($F64,Inputs!$D$6:$E$41,2,FALSE) | S64: =VLOOKUP($E64,Inputs!$A$6:$B$13,2,FALSE)*Inputs!$B$2 | T64: =$L64*$S64 | U64: =$L64+$T64
A65: PKG-03::L-005 | B65: PKG-03 | C65: DEL-03.06 | D65: L-005 | E65: E | F65: PKG-03 | G65: DEL-03.06 | H65: Specialist CCTV survey and reporting | I65: 1 | J65: LS | K65: 32000 | L65: 32000 | M65: CAD | N65: ALLOWANCE | O65: A-013 | P65: LOW | Q65: CCTV inspection of storm drainage pipes; defect analysis; remediation recommendations; video file archival; assumes 800-1200 LM survey extent | R65: =VLOOKUP($F65,Inputs!$D$6:$E$41,2,FALSE) | S65: =VLOOKUP($E65,Inputs!$A$6:$B$13,2,FALSE)*Inputs!$B$2 | T65: =$L65*$S65 | U65: =$L65+$T65
A66: PKG-03::L-006 | B66: PKG-03 | C66: DEL-03.01 | D66: L-006 | E66: MAT | F66: PKG-03 | G66: DEL-03.01 | H66: Storm drainage pipe and fittings | I66: 1 | J66: LS | K66: 185000 | L66: 185000 | M66: CAD | N66: ALLOWANCE | O66: A-001 + A-009 | P66: LOW | Q66: HDPE/concrete/PVC storm pipes DN150-DN600; approximately 800-1200 LM total; includes fittings; bedding materials; pipe material pricing per A-009 | R66: =VLOOKUP($F66,Inputs!$D$6:$E$41,2,FALSE) | S66: =VLOOKUP($E66,Inputs!$A$6:$B$13,2,FALSE)*Inputs!$B$2 | T66: =$L66*$S66 | U66: =$L66+$T66
A67: PKG-03::L-007 | B67: PKG-03 | C67: DEL-03.01 | D67: L-007 | E67: MAT | F67: PKG-03 | G67: DEL-03.01 | H67: Manholes and catch basins | I67: 1 | J67: LS | K67: 155000 | L67: 155000 | M67: CAD | N67: ALLOWANCE | O67: A-002 + A-009 | P67: LOW | Q67: Precast concrete manholes (15-25 units) and catch basins (25-40 units); includes frames/covers/castings; manhole pricing per A-009 | R67: =VLOOKUP($F67,Inputs!$D$6:$E$41,2,FALSE) | S67: =VLOOKUP($E67,Inputs!$A$6:$B$13,2,FALSE)*Inputs!$B$2 | T67: =$L67*$S67 | U67: =$L67+$T67
A68: PKG-03::L-008 | B68: PKG-03 | C68: DEL-03.04 | D68: L-008 | E68: MAT | F68: PKG-03 | G68: DEL-03.04 | H68: Oil-Water Separator equipment and instrumentation | I68: 1 | J68: LS | K68: 135000 | L68: 135000 | M68: CAD | N68: ALLOWANCE | O68: A-003 + A-009 | P68: LOW | Q68: Packaged OWS unit 50-100 L/s capacity; includes internals; instrumentation (level; flow; oil layer monitors; alarms); piping/sumps; OWS pricing per A-009 and A-023 discharge limits | R68: =VLOOKUP($F68,Inputs!$D$6:$E$41,2,FALSE) | S68: =VLOOKUP($E68,Inputs!$A$6:$B$13,2,FALSE)*Inputs!$B$2 | T68: =$L68*$S68 | U68: =$L68+$T68
A69: PKG-03::L-009 | B69: PKG-03 | C69: DEL-03.01 | D69: L-009 | E69: MAT | F69: PKG-03 | G69: DEL-03.01 | H69: Duct bank materials | I69: 1 | J69: LS | K69: 95000 | L69: 95000 | M69: CAD | N69: ALLOWANCE | O69: A-004 + A-009 | P69: LOW | Q69: PVC/HDPE conduit 400-600 LM total; concrete encasement; pull boxes (10-15 units); conduit pricing per A-009 | R69: =VLOOKUP($F69,Inputs!$D$6:$E$41,2,FALSE) | S69: =VLOOKUP($E69,Inputs!$A$6:$B$13,2,FALSE)*Inputs!$B$2 | T69: =$L69*$S69 | U69: =$L69+$T69
A70: PKG-03::L-010 | B70: PKG-03 | C70: DEL-03.01 | D70: L-010 | E70: CD | F70: PKG-03 | G70: DEL-03.01 | H70: Storm drainage installation | I70: 1 | J70: LS | K70: 385000 | L70: 385000 | M70: CAD | N70: ALLOWANCE | O70: A-001 + A-010 + A-011 + A-015 | P70: LOW | Q70: Excavation (1500-2500 m³); pipe laying (800-1200 LM); manhole/catch basin installation; backfill/compaction; includes dewatering (A-016); shoring (A-017); labor/equipment per A-010/A-011 | R70: =VLOOKUP($F70,Inputs!$D$6:$E$41,2,FALSE) | S70: =VLOOKUP($E70,Inputs!$A$6:$B$13,2,FALSE)*Inputs!$B$2 | T70: =$L70*$S70 | U70: =$L70+$T70
A71: PKG-03::L-011 | B71: PKG-03 | C71: DEL-03.04 | D71: L-011 | E71: CD | F71: PKG-03 | G71: DEL-03.04 | H71: OWS installation | I71: 1 | J71: LS | K71: 95000 | L71: 95000 | M71: CAD | N71: ALLOWANCE | O71: A-003 + A-010 + A-011 | P71: LOW | Q71: OWS equipment installation; piping connections; instrumentation installation; sump construction; electrical tie-ins; testing support; labor/equipment per A-010/A-011 | R71: =VLOOKUP($F71,Inputs!$D$6:$E$41,2,FALSE) | S71: =VLOOKUP($E71,Inputs!$A$6:$B$13,2,FALSE)*Inputs!$B$2 | T71: =$L71*$S71 | U71: =$L71+$T71
A72: PKG-03::L-012 | B72: PKG-03 | C72: DEL-03.01 | D72: L-012 | E72: CD | F72: PKG-03 | G72: DEL-03.01 | H72: Duct bank installation | I72: 1 | J72: LS | K72: 145000 | L72: 145000 | M72: CAD | N72: ALLOWANCE | O72: A-004 + A-010 + A-011 + A-015 | P72: LOW | Q72: Trench excavation; conduit installation; concrete encasement; pull box installation; backfill/compaction; includes shoring/dewatering; labor/equipment per A-010/A-011 | R72: =VLOOKUP($F72,Inputs!$D$6:$E$41,2,FALSE) | S72: =VLOOKUP($E72,Inputs!$A$6:$B$13,2,FALSE)*Inputs!$B$2 | T72: =$L72*$S72 | U72: =$L72+$T72
... A74: PKG-03::L-014 | B74: PKG-03 | C74: DEL-03.05 | D74: L-014 | E74: CD | F74: PKG-03 | G74: DEL-03.05 | H74: Installation support and site works | I74: 1 | J74: LS | K74: 85000 | L74: 85000 | M74: CAD | N74: ALLOWANCE | O74: A-018 + A-019 | P74: LOW | Q74: Traffic management and access control; environmental protection during construction (erosion/sediment control; SWPPP); site restoration; cleanup; assumptions per A-018 and A-019 | R74: =VLOOKUP($F74,Inputs!$D$6:$E$41,2,FALSE) | S74: =VLOOKUP($E74,Inputs!$A$6:$B$13,2,FALSE)*Inputs!$B$2 | T74: =$L74*$S74 | U74: =$L74+$T74
A75: PKG-03::L-015 | B75: PKG-03 | D75: L-015 | E75: CI | F75: PKG-03 | H75: Construction Indirects (factor-based) | I75: 1 | J75: LS | K75: 175500 | L75: 175500 | M75: CAD | N75: PARAMETRIC | O75: D-009 (factor=0.18) | P75: MEDIUM | Q75: CI = 0.18 × CD ($975k); includes site supervision; temporary facilities; HSE; QA/QC field inspection; construction management; small tools; per fallback typical model | R75: =VLOOKUP($F75,Inputs!$D$6:$E$41,2,FALSE) | S75: =VLOOKUP($E75,Inputs!$A$6:$B$13,2,FALSE)*Inputs!$B$2 | T75: =$L75*$S75 | U75: =$L75+$T75
A76: PKG-03::L-016 | B76: PKG-03 | D76: L-016 | E76: P | F76: PKG-03 | H76: Procurement Services (factor-based) | I76: 1 | J76: LS | K76: 11400 | L76: 11400 | M76: CAD | N76: PARAMETRIC | O76: D-009 (factor=0.02) | P76: MEDIUM | Q76: P = 0.02 × MAT ($570k); includes material sourcing; PO processing; expediting; receiving inspection; material documentation; per fallback typical model | R76: =VLOOKUP($F76,Inputs!$D$6:$E$41,2,FALSE) | S76: =VLOOKUP($E76,Inputs!$A$6:$B$13,2,FALSE)*Inputs!$B$2 | T76: =$L76*$S76 | U76: =$L76+$T76
A77: PKG-03::L-017 | B77: PKG-03 | D77: L-017 | E77: PM | F77: PKG-03 | H77: EPCM/Project Management (factor-based) | I77: 1 | J77: LS | K77: 103000 | L77: 103000 | M77: CAD | N77: PARAMETRIC | O77: D-009 (factor=0.06) | P77: MEDIUM | Q77: PM = 0.06 × (CD + CI + MAT) ($1721k); includes project management; engineering management; schedule/cost control; contract administration; stakeholder coordination; per fallback typical model | R77: =VLOOKUP($F77,Inputs!$D$6:$E$41,2,FALSE) | S77: =VLOOKUP($E77,Inputs!$A$6:$B$13,2,FALSE)*Inputs!$B$2 | T77: =$L77*$S77 | U77: =$L77+$T77
A78: PKG-03::L-018 | B78: PKG-03 | D78: L-018 | E78: COM | F78: PKG-03 | H78: Commissioning (factor-based) | I78: 1 | J78: LS | K78: 52000 | L78: 52000 | M78: CAD | N78: PARAMETRIC | O78: D-009 (factor=0.03) | P78: MEDIUM | Q78: COM = 0.03 × (CD + CI + MAT) ($1721k); includes pre-commissioning; performance testing per DEL-03.05 (pressure testing; CCTV; OWS performance verification; as-built survey); system acceptance; handover; per fallback typical model | R78: =VLOOKUP($F78,Inputs!$D$6:$E$41,2,FALSE) | S78: =VLOOKUP($E78,Inputs!$A$6:$B$13,2,FALSE)*Inputs!$B$2 | T78: =$L78*$S78 | U78: =$L78+$T78
A79: PKG-04::L001 | B79: PKG-04 | C79: DEL-04.01 | D79: L001 | E79: E | F79: PKG-04 | G79: DEL-04.01 | H79: Pavement Design Drawing Set - CAD drafting (paving layout plans sections details line marking plans) | I79: 1 | J79: LS | K79: 32000 | L79: 32000 | M79: CAD | N79: ALLOWANCE | O79: A-007 | P79: LOW | Q79: ~10-12 sheets at $3k/sheet average | R79: =VLOOKUP($F79,Inputs!$D$6:$E$41,2,FALSE) | S79: =VLOOKUP($E79,Inputs!$A$6:$B$13,2,FALSE)*Inputs!$B$2 | T79: =$L79*$S79 | U79: =$L79+$T79
A80: PKG-04::L002 | B80: PKG-04 | C80: DEL-04.02 | D80: L002 | E80: E | F80: PKG-04 | G80: DEL-04.02 | H80: Pavement Technical Specification - specification writing (asphalt concrete base line marking QC specs) | I80: 1 | J80: LS | K80: 8000 | L80: 8000 | M80: CAD | N80: ALLOWANCE | O80: A-008 | P80: LOW | Q80: ~50 hours at $160/hr | R80: =VLOOKUP($F80,Inputs!$D$6:$E$41,2,FALSE) | S80: =VLOOKUP($E80,Inputs!$A$6:$B$13,2,FALSE)*Inputs!$B$2 | T80: =$L80*$S80 | U80: =$L80+$T80
A81: PKG-04::L003 | B81: PKG-04 | C81: DEL-04.03 | D81: L003 | E81: E | F81: PKG-04 | G81: DEL-04.03 | H81: Pavement Design Calculations - layer thickness design load analysis structural capacity verification | I81: 1 | J81: LS | K81: 12000 | L81: 12000 | M81: CAD | N81: ALLOWANCE | O81: A-009 | P81: LOW | Q81: ~60 hours at $200/hr | R81: =VLOOKUP($F81,Inputs!$D$6:$E$41,2,FALSE) | S81: =VLOOKUP($E81,Inputs!$A$6:$B$13,2,FALSE)*Inputs!$B$2 | T81: =$L81*$S81 | U81: =$L81+$T81
A82: PKG-04::L004 | B82: PKG-04 | C82: DEL-04.04 | D82: L004 | E82: E | F82: PKG-04 | G82: DEL-04.04 | H82: Pavement QA/QC Records Compilation - test records documentation acceptance records | I82: 1 | J82: LS | K82: 10000 | L82: 10000 | M82: CAD | N82: ALLOWANCE | O82: A-010 | P82: LOW | Q82: ~80 hours at $125/hr | R82: =VLOOKUP($F82,Inputs!$D$6:$E$41,2,FALSE) | S82: =VLOOKUP($E82,Inputs!$A$6:$B$13,2,FALSE)*Inputs!$B$2 | T82: =$L82*$S82 | U82: =$L82+$T82
A83: PKG-04::L005 | B83: PKG-04 | D83: L005 | E83: MAT | F83: PKG-04 | H83: Asphalt Concrete Supply - dense-graded HMA for wearing/binder/base courses (~35000 m² × 150mm avg) | I83: 1 | J83: LS | K83: 700000 | L83: 700000 | M83: CAD | N83: ALLOWANCE | O83: A-001 | P83: LOW | Q83: ~8000 tonnes at $85/tonne | R83: =VLOOKUP($F83,Inputs!$D$6:$E$41,2,FALSE) | S83: =VLOOKUP($E83,Inputs!$A$6:$B$13,2,FALSE)*Inputs!$B$2 | T83: =$L83*$S83 | U83: =$L83+$T83
A84: PKG-04::L006 | B84: PKG-04 | D84: L006 | E84: CD | F84: PKG-04 | H84: Asphalt Paving Installation - place and compact wearing/binder/base courses (~35000 m²) | I84: 1 | J84: LS | K84: 525000 | L84: 525000 | M84: CAD | N84: ALLOWANCE | O84: A-001 | P84: LOW | Q84: $15/m² placement + compaction labor | R84: =VLOOKUP($F84,Inputs!$D$6:$E$41,2,FALSE) | S84: =VLOOKUP($E84,Inputs!$A$6:$B$13,2,FALSE)*Inputs!$B$2 | T84: =$L84*$S84 | U84: =$L84+$T84
A85: PKG-04::L007 | B85: PKG-04 | D85: L007 | E85: MAT | F85: PKG-04 | H85: Concrete Paving Materials - PCC for heavy load areas (~10000 m² × 200mm) | I85: 1 | J85: LS | K85: 400000 | L85: 400000 | M85: CAD | N85: ALLOWANCE | O85: A-002 | P85: LOW | Q85: $40/m² material (concrete reinforcement joints) | R85: =VLOOKUP($F85,Inputs!$D$6:$E$41,2,FALSE) | S85: =VLOOKUP($E85,Inputs!$A$6:$B$13,2,FALSE)*Inputs!$B$2 | T85: =$L85*$S85 | U85: =$L85+$T85
A86: PKG-04::L008 | B86: PKG-04 | D86: L008 | E86: CD | F86: PKG-04 | H86: Concrete Paving Installation - place finish cure joint sawing (~10000 m²) | I86: 1 | J86: LS | K86: 700000 | L86: 700000 | M86: CAD | N86: ALLOWANCE | O86: A-002 | P86: LOW | Q86: $70/m² placement finishing curing | R86: =VLOOKUP($F86,Inputs!$D$6:$E$41,2,FALSE) | S86: =VLOOKUP($E86,Inputs!$A$6:$B$13,2,FALSE)*Inputs!$B$2 | T86: =$L86*$S86 | U86: =$L86+$T86
A87: PKG-04::L009 | B87: PKG-04 | D87: L009 | E87: MAT | F87: PKG-04 | H87: Granular Base Course Material - crushed aggregate base (~45000 m² × 200mm) | I87: 1 | J87: LS | K87: 315000 | L87: 315000 | M87: CAD | N87: ALLOWANCE | O87: A-011 | P87: LOW | Q87: ~13500 tonnes at $23/tonne delivered | R87: =VLOOKUP($F87,Inputs!$D$6:$E$41,2,FALSE) | S87: =VLOOKUP($E87,Inputs!$A$6:$B$13,2,FALSE)*Inputs!$B$2 | T87: =$L87*$S87 | U87: =$L87+$T87
A88: PKG-04::L010 | B88: PKG-04 | D88: L010 | E88: CD | F88: PKG-04 | H88: Base Course Placement and Compaction (~45000 m²) | I88: 1 | J88: LS | K88: 180000 | L88: 180000 | M88: CAD | N88: ALLOWANCE | O88: A-011 | P88: LOW | Q88: $4/m² spread and compact | R88: =VLOOKUP($F88,Inputs!$D$6:$E$41,2,FALSE) | S88: =VLOOKUP($E88,Inputs!$A$6:$B$13,2,FALSE)*Inputs!$B$2 | T88: =$L88*$S88 | U88: =$L88+$T88
A89: PKG-04::L011 | B89: PKG-04 | D89: L011 | E89: MAT | F89: PKG-04 | H89: Curb and Gutter Materials - precast or cast-in-place concrete (~2500 lm) | I89: 1 | J89: LS | K89: 75000 | L89: 75000 | M89: CAD | N89: ALLOWANCE | O89: A-003 | P89: LOW | Q89: $30/lm material | R89: =VLOOKUP($F89,Inputs!$D$6:$E$41,2,FALSE) | S89: =VLOOKUP($E89,Inputs!$A$6:$B$13,2,FALSE)*Inputs!$B$2 | T89: =$L89*$S89 | U89: =$L89+$T89
A90: PKG-04::L012 | B90: PKG-04 | D90: L012 | E90: CD | F90: PKG-04 | H90: Curb and Gutter Installation - forming placing finishing (~2500 lm) | I90: 1 | J90: LS | K90: 125000 | L90: 125000 | M90: CAD | N90: ALLOWANCE | O90: A-003 | P90: LOW | Q90: $50/lm labor equipment | R90: =VLOOKUP($F90,Inputs!$D$6:$E$41,2,FALSE) | S90: =VLOOKUP($E90,Inputs!$A$6:$B$13,2,FALSE)*Inputs!$B$2 | T90: =$L90*$S90 | U90: =$L90+$T90
A91: PKG-04::L013 | B91: PKG-04 | D91: L013 | E91: MAT | F91: PKG-04 | H91: Sidewalk Materials - concrete (~600 m² × 100mm) | I91: 1 | J91: LS | K91: 18000 | L91: 18000 | M91: CAD | N91: ALLOWANCE | O91: A-004 | P91: LOW | Q91: $30/m² material | R91: =VLOOKUP($F91,Inputs!$D$6:$E$41,2,FALSE) | S91: =VLOOKUP($E91,Inputs!$A$6:$B$13,2,FALSE)*Inputs!$B$2 | T91: =$L91*$S91 | U91: =$L91+$T91
A92: PKG-04::L014 | B92: PKG-04 | D92: L014 | E92: CD | F92: PKG-04 | H92: Sidewalk Installation - form place finish cure (~600 m²) | I92: 1 | J92: LS | K92: 30000 | L92: 30000 | M92: CAD | N92: ALLOWANCE | O92: A-004 | P92: LOW | Q92: $50/m² labor | R92: =VLOOKUP($F92,Inputs!$D$6:$E$41,2,FALSE) | S92: =VLOOKUP($E92,Inputs!$A$6:$B$13,2,FALSE)*Inputs!$B$2 | T92: =$L92*$S92 | U92: =$L92+$T92
A93: PKG-04::L015 | B93: PKG-04 | D93: L015 | E93: MAT | F93: PKG-04 | H93: Line Marking Materials - thermoplastic and paint (~6000 lm) | I93: 1 | J93: LS | K93: 24000 | L93: 24000 | M93: CAD | N93: ALLOWANCE | O93: A-006 | P93: LOW | Q93: $4/lm material | R93: =VLOOKUP($F93,Inputs!$D$6:$E$41,2,FALSE) | S93: =VLOOKUP($E93,Inputs!$A$6:$B$13,2,FALSE)*Inputs!$B$2 | T93: =$L93*$S93 | U93: =$L93+$T93
A94: PKG-04::L016 | B94: PKG-04 | D94: L016 | E94: CD | F94: PKG-04 | H94: Line Marking Application - traffic control safety markings parking stalls (~6000 lm) | I94: 1 | J94: LS | K94: 18000 | L94: 18000 | M94: CAD | N94: ALLOWANCE | O94: A-006 | P94: LOW | Q94: $3/lm labor equipment | R94: =VLOOKUP($F94,Inputs!$D$6:$E$41,2,FALSE) | S94: =VLOOKUP($E94,Inputs!$A$6:$B$13,2,FALSE)*Inputs!$B$2 | T94: =$L94*$S94 | U94: =$L94+$T94
... A107: PKG-04::L029 | B107: PKG-04 | D107: L029 | E107: COM | F107: PKG-04 | H107: Testing and Verification - final verification testing reporting | I107: 1 | J107: LS | K107: 109000 | L107: 109000 | M107: CAD | N107: PARAMETRIC | O107: D-008 | P107: LOW | Q107: 3% of (CD+CI+MAT) base | R107: =VLOOKUP($F107,Inputs!$D$6:$E$41,2,FALSE) | S107: =VLOOKUP($E107,Inputs!$A$6:$B$13,2,FALSE)*Inputs!$B$2 | T107: =$L107*$S107 | U107: =$L107+$T107
A108: PKG-05::L001 | B108: PKG-05 | C108: DEL-05.01 | D108: L001 | E108: E | F108: PKG-05 | G108: DEL-05.01 | H108: Concrete Structures Design Drawing Set - structural CAD drafting (22 sheets) | I108: 1 | J108: LS | K108: 85000 | L108: 85000 | M108: CAD | N108: ALLOWANCE | O108: A-001 | P108: LOW | Q108: Allowance for drawing production without vendor quotes; includes foundations containment walls equipment pads reinforcement | R108: =VLOOKUP($F108,Inputs!$D$6:$E$41,2,FALSE) | S108: =VLOOKUP($E108,Inputs!$A$6:$B$13,2,FALSE)*Inputs!$B$2 | T108: =$L108*$S108 | U108: =$L108+$T108
A109: PKG-05::L002 | B109: PKG-05 | C109: DEL-05.02 | D109: L002 | E109: E | F109: PKG-05 | G109: DEL-05.02 | H109: Concrete Structures Technical Specification - specification writing (3 specifications) | I109: 1 | J109: LS | K109: 45000 | L109: 45000 | M109: CAD | N109: ALLOWANCE | O109: A-002 | P109: LOW | Q109: Allowance for concrete reinforcement formwork specifications | R109: =VLOOKUP($F109,Inputs!$D$6:$E$41,2,FALSE) | S109: =VLOOKUP($E109,Inputs!$A$6:$B$13,2,FALSE)*Inputs!$B$2 | T109: =$L109*$S109 | U109: =$L109+$T109
A110: PKG-05::L003 | B110: PKG-05 | C110: DEL-05.03 | D110: L003 | E110: E | F110: PKG-05 | G110: DEL-05.03 | H110: Concrete Structures Design Calculations - structural engineering (foundation containment seismic) | I110: 1 | J110: LS | K110: 120000 | L110: 120000 | M110: CAD | N110: ALLOWANCE | O110: A-003 | P110: LOW | Q110: Allowance for design calculations including tank foundations containment walls seismic analysis | R110: =VLOOKUP($F110,Inputs!$D$6:$E$41,2,FALSE) | S110: =VLOOKUP($E110,Inputs!$A$6:$B$13,2,FALSE)*Inputs!$B$2 | T110: =$L110*$S110 | U110: =$L110+$T110
A111: PKG-05::L004 | B111: PKG-05 | C111: DEL-05.04 | D111: L004 | E111: PM | F111: PKG-05 | G111: DEL-05.04 | H111: Installation & Test Records - QA/QC documentation and coordination | I111: 1 | J111: LS | K111: 35000 | L111: 35000 | M111: CAD | N111: ALLOWANCE | O111: A-004 | P111: LOW | Q111: Allowance for concrete pour records cylinder test coordination rebar inspection records | R111: =VLOOKUP($F111,Inputs!$D$6:$E$41,2,FALSE) | S111: =VLOOKUP($E111,Inputs!$A$6:$B$13,2,FALSE)*Inputs!$B$2 | T111: =$L111*$S111 | U111: =$L111+$T111
A112: PKG-05::L005 | B112: PKG-05 | D112: L005 | E112: MAT | F112: PKG-05 | H112: Tank Foundation Concrete - ready-mix supply for 3x15000 MT tank ring walls | I112: 450 | J112: m3 | K112: 220 | L112: 99000 | M112: CAD | N112: ALLOWANCE | O112: A-005 | P112: LOW | Q112: 450 m3 derived from 3 tanks x 150 m3 each; ring wall type per D-011 | R112: =VLOOKUP($F112,Inputs!$D$6:$E$41,2,FALSE) | S112: =VLOOKUP($E112,Inputs!$A$6:$B$13,2,FALSE)*Inputs!$B$2 | T112: =$L112*$S112 | U112: =$L112+$T112
A113: PKG-05::L006 | B113: PKG-05 | D113: L006 | E113: CD | F113: PKG-05 | H113: Tank Foundation Installation - concrete placement forming curing | I113: 450 | J113: m3 | K113: 180 | L113: 81000 | M113: CAD | N113: ALLOWANCE | O113: A-005 | P113: LOW | Q113: Installation rate for slab/foundation work | R113: =VLOOKUP($F113,Inputs!$D$6:$E$41,2,FALSE) | S113: =VLOOKUP($E113,Inputs!$A$6:$B$13,2,FALSE)*Inputs!$B$2 | T113: =$L113*$S113 | U113: =$L113+$T113
A114: PKG-05::L007 | B114: PKG-05 | D114: L007 | E114: MAT | F114: PKG-05 | H114: Containment Wall Concrete - high-quality ready-mix for secondary containment | I114: 600 | J114: m3 | K114: 240 | L114: 144000 | M114: CAD | N114: ALLOWANCE | O114: A-006 | P114: LOW | Q114: 600 m3 for perimeter walls supporting OBJ-7 Environmental Protection; premium mix for low permeability | R114: =VLOOKUP($F114,Inputs!$D$6:$E$41,2,FALSE) | S114: =VLOOKUP($E114,Inputs!$A$6:$B$13,2,FALSE)*Inputs!$B$2 | T114: =$L114*$S114 | U114: =$L114+$T114
A115: PKG-05::L008 | B115: PKG-05 | D115: L008 | E115: CD | F115: PKG-05 | H115: Containment Wall Installation - concrete placement with waterstops complex formwork | I115: 600 | J115: m3 | K115: 350 | L115: 210000 | M115: CAD | N115: ALLOWANCE | O115: A-006 | P115: LOW | Q115: Higher rate for wall construction with waterstops and containment-grade finishing | R115: =VLOOKUP($F115,Inputs!$D$6:$E$41,2,FALSE) | S115: =VLOOKUP($E115,Inputs!$A$6:$B$13,2,FALSE)*Inputs!$B$2 | T115: =$L115*$S115 | U115: =$L115+$T115
A116: PKG-05::L009 | B116: PKG-05 | D116: L009 | E116: MAT | F116: PKG-05 | H116: Equipment Pad Concrete - ready-mix for pump metering railcar unloading pads | I116: 200 | J116: m3 | K116: 230 | L116: 46000 | M116: CAD | N116: ALLOWANCE | O116: A-007 | P116: LOW | Q116: 200 m3 for various equipment pads; includes anchor bolt blockouts | R116: =VLOOKUP($F116,Inputs!$D$6:$E$41,2,FALSE) | S116: =VLOOKUP($E116,Inputs!$A$6:$B$13,2,FALSE)*Inputs!$B$2 | T116: =$L116*$S116 | U116: =$L116+$T116
...

Sheet BOE_Reference
A1: BOE reference tables (from Project_BOE.md) | H1: Home
A3: Executive summary metrics | D3: Counts
A4: Metric | B4: Value | D4: Packages | E4: 36
A5: **Total Estimate** | B5: **$117.1M CAD** | D5: Deliverables | E5: 202
A6: Base Estimate | B6: $92,416,406 CAD | D6: Line items | E6: 867
A7: Contingency | B7: ~$24.7M CAD (~26.7% blended)
A8: Currency | B8: CAD (Canadian dollars)
A9: Pricing Date | B9: January 2026
A10: Estimate Class | B10: Class 5 (Order of Magnitude)
A11: Overall Confidence | B11: LOW
A12: Accuracy Range | B12: -30% / +50%
A14: Package coverage summary
A15: Category | B15: Packages | C15: Base Cost | D15: % of Total
A16: Site & Civil | B16: PKG-00 to PKG-04 | C16: $12.5M | D16: 13.5%
A17: Structural | B17: PKG-05 to PKG-09 | C17: $13.7M | D17: 14.8%
A18: Mechanical | B18: PKG-10 to PKG-16 | C18: $36.0M | D18: 39.0%
A19: Electrical & I&C | B19: PKG-17 to PKG-20 | C19: $8.4M | D19: 9.1%
A20: Buildings & Protection | B20: PKG-21 to PKG-26 | C20: $9.3M | D20: 10.1%
A21: Project Execution | B21: PKG-27 to PKG-35 | C21: $12.5M | D21: 13.5%
A22: **TOTAL** | B22: **36 Packages** | C22: **$92.4M** | D22: **100%**
A25: CBS summary
A26: CBS | B26: Description | C26: Amount (CAD) | D26: % of Total
A27: MAT | B27: Materials | C27: $41,045,785 | D27: 44.4%
A28: CD | B28: Construction Directs | C28: $26,933,520 | D28: 29.1%
A29: E | B29: Engineering | C29: $8,640,165 | D29: 9.4%
A30: PM | B30: Project Management | C30: $5,821,748 | D30: 6.3%
A31: CI | B31: Construction Indirects | C31: $5,816,043 | D31: 6.3%
A32: COM | B32: Commissioning | C32: $3,004,199 | D32: 3.3%
A33: P | B33: Procurement | C33: $921,946 | D33: 1.0%
A34: FRT | B34: Freight | C34: $233,000 | D34: 0.3%
A35: **BASE TOTAL** | C35: **$92,416,406** | D35: **100%**
A37: Pricing method distribution
A38: Method | B38: Line Items | C38: % of Items | D38: Remarks
A39: ALLOWANCE | B39: 689 | C39: 79.5% | D39: Lump-sum placeholders without vendor validation
A40: PARAMETRIC | B40: 154 | C40: 17.8% | D40: Factor-based calculations (indirects, PM, etc.)
A41: RATE_TABLE | B41: 11 | C41: 1.3% | D41: Limited rate table pricing
A42: QUOTE | B42: 0 | C42: 0% | D42: No vendor quotes available
A43: **TOTAL** | B43: **867** | C43: **100%**
A46: Contingency by CBS (as stated in BOE)
A47: CBS | B47: Base (CAD) | C47: Contingency Rate | D47: Contingency (CAD)
A48: E | B48: $8,640,165 | C48: 15% | D48: $1,296,000
A49: PM | B49: $5,821,748 | C49: 15% | D49: $873,000
A50: P | B50: $921,946 | C50: 15% | D50: $138,000
A51: MAT | B51: $41,045,785 | C51: 20% | D51: $8,209,000
A52: FRT | B52: $233,000 | C52: 20% | D52: $47,000
A53: CD | B53: $26,933,520 | C53: 25% | D53: $6,733,000
A54: CI | B54: $5,816,043 | C54: 25% | D54: $1,454,000
A55: COM | B55: $3,004,199 | C55: 30% | D55: $901,000
A56: **TOTAL** | B56: **$92,416,406** | C56: **~26.7%** | D56: **~$24.7M**

Sheet Inputs
A1: Model Inputs / Lookups | L1: Home
A2: Contingency scaling factor | B2: 1 | C2: (1.00 = use BOE bucket rates as-is)
A4: Contingency rates by CBS (from BOE §7.2) | D4: Package category mapping (from BOE §2.3) | G4: Package descriptions (from BOE §12)
A5: CBS | B5: Rate | D5: Package | E5: PackageCategory | G5: Package | H5: Description | I5: Confidence
A6: E | B6: 0.15 | D6: PKG-00 | E6: Site & Civil | G6: PKG-00 | H6: Site Establishment | I6: LOW
A7: PM | B7: 0.15 | D7: PKG-01 | E7: Site & Civil | G7: PKG-01 | H7: Demolition & Removals | I7: LOW
A8: P | B8: 0.15 | D8: PKG-02 | E8: Site & Civil | G8: PKG-02 | H8: Earthworks & Ground Improvement | I8: LOW
A9: MAT | B9: 0.2 | D9: PKG-03 | E9: Site & Civil | G9: PKG-03 | H9: Underground Utilities & Drainage | I9: LOW
A10: FRT | B10: 0.2 | D10: PKG-04 | E10: Site & Civil | G10: PKG-04 | H10: Pavement & Surfacing | I10: LOW
A11: CD | B11: 0.25 | D11: PKG-05 | E11: Structural | G11: PKG-05 | H11: Concrete Structures | I11: LOW
A12: CI | B12: 0.25 | D12: PKG-06 | E12: Structural | G12: PKG-06 | H12: Structural Steelwork | I12: LOW
A13: COM | B13: 0.3 | D13: PKG-07 | E13: Structural | G13: PKG-07 | H13: Rail Works | I13: LOW
D14: PKG-08 | E14: Structural | G14: PKG-08 | H14: Marine Structures | I14: LOW
D15: PKG-09 | E15: Structural | G15: PKG-09 | H15: Marine Outfitting | I15: LOW
D16: PKG-10 | E16: Mechanical | G16: PKG-10 | H16: Railcar Unloading System | I16: LOW
D17: PKG-11 | E17: Mechanical | G17: PKG-11 | H17: Marine Loading System | I17: LOW
D18: PKG-12 | E18: Mechanical | G18: PKG-12 | H18: Product Transfer & Metering | I18: LOW
D19: PKG-13 | E19: Mechanical | G19: PKG-13 | H19: Storage Tanks | I19: LOW
D20: PKG-14 | E20: Mechanical | G20: PKG-14 | H20: Process Piping | I20: LOW
D21: PKG-15 | E21: Mechanical | G21: PKG-15 | H21: Pumps & Rotating Equipment | I21: LOW-MED
D22: PKG-16 | E22: Mechanical | G22: PKG-16 | H22: Valves & Specialty Equipment | I22: LOW
D23: PKG-17 | E23: Electrical & I&C | G23: PKG-17 | H23: Electrical Power Distribution | I23: LOW
D24: PKG-18 | E24: Electrical & I&C | G24: PKG-18 | H24: Lighting | I24: LOW
D25: PKG-19 | E25: Electrical & I&C | G25: PKG-19 | H25: Control Systems | I25: LOW
... D41: PKG-35 | E41: Project Execution | G41: PKG-35 | H41: Training & Handover | I41: LOW
